{"v":"5.0.1","fr":10,"ip":0,"op":100,"w":700,"h":700,"ddd":0,"assets":[],"layers":[{"ind":7,"nm":"Layer_5","ks":{"p":{"a":1,"k":[{"t":0,"s":[45.453,81.75,0],"to":[0,0,0],"ti":[0,0,0],"i":{"x":[0.58],"y":[1]},"o":{"x":[0.42],"y":[0]},"e":[45.453,226.794,0]},{"t":25,"s":[45.453,226.794,0],"to":[0,0,0],"ti":[0,0,0],"i":{"x":[0.58],"y":[1]},"o":{"x":[0.42],"y":[0]},"e":[45.453,81.75,0]},{"t":50,"s":[45.453,81.75,0],"to":[0,0,0],"ti":[0,0,0],"i":{"x":[0.58],"y":[1]},"o":{"x":[0.42],"y":[0]},"e":[45.453,226.794,0]},{"t":75,"s":[45.453,226.794,0],"to":[0,0,0],"ti":[0,0,0],"i":{"x":[0.58],"y":[1]},"o":{"x":[0.42],"y":[0]},"e":[45.453,81.75,0]},{"t":100,"s":[45.453,81.75,0]}]},"a":{"a":0,"k":[208.647,289.556,0]},"s":{"a":0,"k":[100,100,100]},"r":{"a":0,"k":0},"o":{"a":0,"k":100}},"ao":0,"ip":0,"op":100,"st":0,"bm":0,"sr":1,"ty":4,"shapes":[{"ty":"gr","it":[{"ty":"gr","it":[{"ty":"sh","d":1,"ks":{"a":0,"k":{"i":[[0,0],[0,0],[0,3],[0,0],[1.8,0.5],[0,0],[0,-3],[0,0],[-1.8,-0.6]],"o":[[0,0],[2.6,0.8],[0,0],[0,-2.1],[0,0],[-2.6,-0.8],[0,0],[-0.1,2.1],[0,0]],"v":[[166.2,315.2],[201.3,325.8],[206.4,321.3],[206.4,281.4],[203.4,276.9],[168.3,266.3],[163.2,270.8],[163.2,310.7],[166.2,315.2]],"c":true},"hd":false}},{"ty":"gf","t":1,"s":{"a":0,"k":[154.854,274.88]},"e":{"a":0,"k":[234.171,330.887]},"g":{"p":6,"k":{"a":0,"k":[0,0.894,0.616,0.784,0.155,0.741,0.525,0.773,0.344,0.584,0.431,0.761,0.493,0.482,0.373,0.753,0.584,0.447,0.353,0.749,1,0.624,0.631,0.878]}},"hd":false,"o":{"a":0,"k":100},"r":1},{"ty":"tr","p":{"a":0,"k":[184.797,296.05]},"a":{"a":0,"k":[184.797,296.05]},"s":{"a":0,"k":[100,100]},"r":{"a":0,"k":0},"o":{"a":0,"k":100},"sk":{"a":0,"k":0},"sa":{"a":0,"k":0}}],"nm":"Object","hd":false},{"ty":"gr","it":[{"ty":"sh","d":1,"ks":{"a":0,"k":{"i":[[0,0],[0,0],[0,3],[0,0],[-2,0.5],[0,0],[0,-3],[0,0],[1.9,-0.6]],"o":[[0,0],[-2.8,0.8],[0,0],[0,-2.1],[0,0],[2.8,-0.8],[0,0],[-0.1,2.1],[0,0]],"v":[[250.7,315.2],[212,325.8],[206.4,321.3],[206.4,281.4],[209.8,276.9],[248.5,266.3],[254.1,270.8],[254.1,310.7],[250.7,315.2]],"c":true},"hd":false}},{"ty":"gf","t":1,"s":{"a":0,"k":[231.1,296.676]},"e":{"a":0,"k":[202.894,275.361]},"g":{"p":4,"k":{"a":0,"k":[0,0.271,0.192,0.58,0.279,0.294,0.212,0.6,0.636,0.353,0.271,0.659,1,0.447,0.353,0.749]}},"hd":false,"o":{"a":0,"k":100},"r":1},{"ty":"tr","p":{"a":0,"k":[230.25,296.05]},"a":{"a":0,"k":[230.25,296.05]},"s":{"a":0,"k":[100,100]},"r":{"a":0,"k":0},"o":{"a":0,"k":100},"sk":{"a":0,"k":0},"sa":{"a":0,"k":0}}],"nm":"Object","hd":false},{"ty":"gr","it":[{"ty":"sh","d":1,"ks":{"a":0,"k":{"i":[[0,0],[-6.5,2.7],[0,0],[0,0]],"o":[[0,0],[6.5,-2.7],[0,0],[0,0]],"v":[[201.2,325.7],[211.9,325.7],[206.3,312.7],[201.2,325.7]],"c":true},"hd":false}},{"ty":"gf","t":1,"s":{"a":0,"k":[201.223,319.833]},"e":{"a":0,"k":[213.856,319.833]},"g":{"p":4,"k":{"a":0,"k":[0,0.271,0.192,0.58,0.279,0.294,0.212,0.6,0.636,0.353,0.271,0.659,1,0.447,0.353,0.749]}},"hd":false,"o":{"a":0,"k":100},"r":1},{"ty":"tr","p":{"a":0,"k":[207.509,319.8]},"a":{"a":0,"k":[207.509,319.8]},"s":{"a":0,"k":[100,100]},"r":{"a":0,"k":0},"o":{"a":0,"k":100},"sk":{"a":0,"k":0},"sa":{"a":0,"k":0}}],"nm":"Object","hd":false},{"ty":"gr","it":[{"ty":"sh","d":1,"ks":{"a":0,"k":{"i":[[0,0],[-2.9,-0.8],[0.2,-7.2],[0,0],[-1.7,5.5],[-34.5,10.5]],"o":[[2.9,-0.9],[11.2,3.1],[-0.1,4.2],[0,0],[1.6,-4.8],[0,0]],"v":[[201.9,252.9],[210.8,252.8],[253.9,269.8],[205.5,282.8],[163.4,268.8],[201.9,252.9]],"c":true},"hd":false}},{"ty":"gf","t":1,"s":{"a":0,"k":[179.032,264.479]},"e":{"a":0,"k":[253.794,272.621]},"g":{"p":3,"k":{"a":0,"k":[0,0.694,0.553,0.839,0.512,0.514,0.522,0.78,1,0.447,0.353,0.749]}},"hd":false,"o":{"a":0,"k":100},"r":1},{"ty":"tr","p":{"a":0,"k":[208.626,267.506]},"a":{"a":0,"k":[208.626,267.506]},"s":{"a":0,"k":[100,100]},"r":{"a":0,"k":0},"o":{"a":0,"k":100},"sk":{"a":0,"k":0},"sa":{"a":0,"k":0}}],"nm":"Object","hd":false},{"ty":"tr","p":{"a":0,"k":[208.647,289.556]},"a":{"a":0,"k":[208.647,289.556]},"s":{"a":0,"k":[100,100]},"r":{"a":0,"k":0},"o":{"a":0,"k":100},"sk":{"a":0,"k":0},"sa":{"a":0,"k":0}}],"nm":"Object","hd":false}],"ln":"Layer_5"},{"ind":6,"nm":"Layer_4","ks":{"p":{"a":1,"k":[{"t":0,"s":[143.856,361,0],"to":[0,0,0],"ti":[0,0,0],"i":{"x":[0.58],"y":[1]},"o":{"x":[0.42],"y":[0]},"e":[143.856,230.088,0]},{"t":25,"s":[143.856,230.088,0],"to":[0,0,0],"ti":[0,0,0],"i":{"x":[0.58],"y":[1]},"o":{"x":[0.42],"y":[0]},"e":[143.856,361,0]},{"t":50,"s":[143.856,361,0],"to":[0,0,0],"ti":[0,0,0],"i":{"x":[0.58],"y":[1]},"o":{"x":[0.42],"y":[0]},"e":[143.856,230.088,0]},{"t":75,"s":[143.856,230.088,0],"to":[0,0,0],"ti":[0,0,0],"i":{"x":[0.58],"y":[1]},"o":{"x":[0.42],"y":[0]},"e":[143.856,361,0]},{"t":100,"s":[143.856,361,0]}]},"a":{"a":0,"k":[307.05,568.806,0]},"s":{"a":0,"k":[100,100,100]},"r":{"a":0,"k":0},"o":{"a":0,"k":100}},"ao":0,"ip":0,"op":100,"st":0,"bm":0,"sr":1,"ty":4,"shapes":[{"ty":"gr","it":[{"ty":"gr","it":[{"ty":"sh","d":1,"ks":{"a":0,"k":{"i":[[0,0],[0,0],[0,3],[0,0],[1.8,0.5],[0,0],[0,-3],[0,0],[-1.8,-0.5]],"o":[[0,0],[2.6,0.8],[0,0],[0,-2.1],[0,0],[-2.6,-0.8],[0,0],[0,2.1],[0,0]],"v":[[264.6,594.4],[299.7,605],[304.8,600.5],[304.8,560.6],[301.8,556.1],[266.7,545.5],[261.6,550],[261.6,589.9],[264.6,594.4]],"c":true},"hd":false}},{"ty":"gf","t":1,"s":{"a":0,"k":[253.283,554.106]},"e":{"a":0,"k":[332.601,610.114]},"g":{"p":6,"k":{"a":0,"k":[0,0.894,0.616,0.784,0.155,0.741,0.525,0.773,0.344,0.584,0.431,0.761,0.493,0.482,0.373,0.753,0.584,0.447,0.353,0.749,1,0.624,0.631,0.878]}},"hd":false,"o":{"a":0,"k":100},"r":1},{"ty":"tr","p":{"a":0,"k":[283.2,575.25]},"a":{"a":0,"k":[283.2,575.25]},"s":{"a":0,"k":[100,100]},"r":{"a":0,"k":0},"o":{"a":0,"k":100},"sk":{"a":0,"k":0},"sa":{"a":0,"k":0}}],"nm":"Object","hd":false},{"ty":"gr","it":[{"ty":"sh","d":1,"ks":{"a":0,"k":{"i":[[0,0],[0,0],[0,3],[0,0],[-2,0.5],[0,0],[0,-3],[0,0],[2,-0.5]],"o":[[0,0],[-2.8,0.8],[0,0],[0,-2.1],[0,0],[2.8,-0.8],[0,0],[0,2.1],[0,0]],"v":[[349.1,594.4],[310.4,605],[304.8,600.5],[304.8,560.6],[308.2,556.1],[346.9,545.5],[352.5,550],[352.5,589.9],[349.1,594.4]],"c":true},"hd":false}},{"ty":"gf","t":1,"s":{"a":0,"k":[329.529,575.902]},"e":{"a":0,"k":[301.324,554.587]},"g":{"p":4,"k":{"a":0,"k":[0,0.271,0.192,0.58,0.279,0.294,0.212,0.6,0.636,0.353,0.271,0.659,1,0.447,0.353,0.749]}},"hd":false,"o":{"a":0,"k":100},"r":1},{"ty":"tr","p":{"a":0,"k":[328.65,575.25]},"a":{"a":0,"k":[328.65,575.25]},"s":{"a":0,"k":[100,100]},"r":{"a":0,"k":0},"o":{"a":0,"k":100},"sk":{"a":0,"k":0},"sa":{"a":0,"k":0}}],"nm":"Object","hd":false},{"ty":"gr","it":[{"ty":"sh","d":1,"ks":{"a":0,"k":{"i":[[0,0],[-6.5,2.7],[0,0],[0,0]],"o":[[0,0],[6.5,-2.7],[0,0],[0,0]],"v":[[299.7,605],[310.4,605],[304.8,592],[299.7,605]],"c":true},"hd":false}},{"ty":"gf","t":1,"s":{"a":0,"k":[299.653,599.059]},"e":{"a":0,"k":[312.286,599.059]},"g":{"p":4,"k":{"a":0,"k":[0,0.271,0.192,0.58,0.279,0.294,0.212,0.6,0.636,0.353,0.271,0.659,1,0.447,0.353,0.749]}},"hd":false,"o":{"a":0,"k":100},"r":1},{"ty":"tr","p":{"a":0,"k":[306.009,599.1]},"a":{"a":0,"k":[306.009,599.1]},"s":{"a":0,"k":[100,100]},"r":{"a":0,"k":0},"o":{"a":0,"k":100},"sk":{"a":0,"k":0},"sa":{"a":0,"k":0}}],"nm":"Object","hd":false},{"ty":"gr","it":[{"ty":"sh","d":1,"ks":{"a":0,"k":{"i":[[0,0],[-2.9,-0.8],[0.2,-7.2],[0,0],[-1.7,5.5],[-34.5,10.5]],"o":[[2.9,-0.9],[11.2,3.1],[-0.1,4.2],[0,0],[1.6,-4.8],[0,0]],"v":[[300.3,532.1],[309.2,532],[352.3,549],[303.9,562],[261.8,548],[300.3,532.1]],"c":true},"hd":false}},{"ty":"gf","t":1,"s":{"a":0,"k":[277.461,543.705]},"e":{"a":0,"k":[352.224,551.847]},"g":{"p":3,"k":{"a":0,"k":[0,0.694,0.553,0.839,0.512,0.514,0.522,0.78,1,0.447,0.353,0.749]}},"hd":false,"o":{"a":0,"k":100},"r":1},{"ty":"tr","p":{"a":0,"k":[307.026,546.706]},"a":{"a":0,"k":[307.026,546.706]},"s":{"a":0,"k":[100,100]},"r":{"a":0,"k":0},"o":{"a":0,"k":100},"sk":{"a":0,"k":0},"sa":{"a":0,"k":0}}],"nm":"Object","hd":false},{"ty":"tr","p":{"a":0,"k":[307.05,568.806]},"a":{"a":0,"k":[307.05,568.806]},"s":{"a":0,"k":[100,100]},"r":{"a":0,"k":0},"o":{"a":0,"k":100},"sk":{"a":0,"k":0},"sa":{"a":0,"k":0}}],"nm":"Object","hd":false}],"ln":"Layer_4"},{"ind":5,"nm":"Layer_2","ks":{"p":{"a":1,"k":[{"t":0,"s":[551.803,411.715,0],"to":[0,0,0],"ti":[0,0,0],"i":{"x":[0.58],"y":[1]},"o":{"x":[0.42],"y":[0]},"e":[551.803,336.615,0]},{"t":16.7,"s":[551.803,336.615,0],"to":[0,0,0],"ti":[0,0,0],"i":{"x":[0.58],"y":[1]},"o":{"x":[0.42],"y":[0]},"e":[551.803,411.715,0]},{"t":33.3,"s":[551.803,411.715,0],"to":[0,0,0],"ti":[0,0,0],"i":{"x":[0.58],"y":[1]},"o":{"x":[0.42],"y":[0]},"e":[551.803,336.615,0]},{"t":50,"s":[551.803,336.615,0],"to":[0,0,0],"ti":[0,0,0],"i":{"x":[0.58],"y":[1]},"o":{"x":[0.42],"y":[0]},"e":[551.803,411.715,0]},{"t":66.7,"s":[551.803,411.715,0],"to":[0,0,0],"ti":[0,0,0],"i":{"x":[0.58],"y":[1]},"o":{"x":[0.42],"y":[0]},"e":[551.803,336.615,0]},{"t":83.3,"s":[551.803,336.615,0],"to":[0,0,0],"ti":[0,0,0],"i":{"x":[0.58],"y":[1]},"o":{"x":[0.42],"y":[0]},"e":[551.803,411.715,0]},{"t":100,"s":[551.803,411.715,0]}]},"a":{"a":0,"k":[612.25,441.406,0]},"s":{"a":0,"k":[100,100,100]},"r":{"a":0,"k":0},"o":{"a":0,"k":100}},"ao":0,"ip":0,"op":100,"st":0,"bm":0,"sr":1,"ty":4,"shapes":[{"ty":"gr","it":[{"ty":"gr","it":[{"ty":"sh","d":1,"ks":{"a":0,"k":{"i":[[0,0],[0,0],[0,3],[0,0],[1.8,0.5],[0,0],[0,-3],[0,0],[-1.8,-0.5]],"o":[[0,0],[2.6,0.8],[0,0],[0,-2.1],[0,0],[-2.6,-0.8],[0,0],[0,2.1],[0,0]],"v":[[569.8,467],[604.9,477.6],[610,473.1],[610,433.2],[607,428.7],[571.9,418.1],[566.8,422.6],[566.8,462.5],[569.8,467]],"c":true},"hd":false}},{"ty":"gf","t":1,"s":{"a":0,"k":[558.5,426.731]},"e":{"a":0,"k":[637.817,482.739]},"g":{"p":6,"k":{"a":0,"k":[0,0.894,0.616,0.784,0.155,0.741,0.525,0.773,0.344,0.584,0.431,0.761,0.493,0.482,0.373,0.753,0.584,0.447,0.353,0.749,1,0.624,0.631,0.878]}},"hd":false,"o":{"a":0,"k":100},"r":1},{"ty":"tr","p":{"a":0,"k":[588.4,447.85]},"a":{"a":0,"k":[588.4,447.85]},"s":{"a":0,"k":[100,100]},"r":{"a":0,"k":0},"o":{"a":0,"k":100},"sk":{"a":0,"k":0},"sa":{"a":0,"k":0}}],"nm":"Object","hd":false},{"ty":"gr","it":[{"ty":"sh","d":1,"ks":{"a":0,"k":{"i":[[0,0],[0,0],[0,3],[0,0],[-2,0.5],[0,0],[0,-3],[0,0],[2,-0.5]],"o":[[0,0],[-2.8,0.8],[0,0],[0,-2.1],[0,0],[2.8,-0.8],[0,0],[0,2.1],[0,0]],"v":[[654.3,467],[615.6,477.6],[610,473.1],[610,433.2],[613.4,428.7],[652.1,418.1],[657.7,422.6],[657.7,462.5],[654.3,467]],"c":true},"hd":false}},{"ty":"gf","t":1,"s":{"a":0,"k":[634.746,448.528]},"e":{"a":0,"k":[606.54,427.213]},"g":{"p":4,"k":{"a":0,"k":[0,0.271,0.192,0.58,0.279,0.294,0.212,0.6,0.636,0.353,0.271,0.659,1,0.447,0.353,0.749]}},"hd":false,"o":{"a":0,"k":100},"r":1},{"ty":"tr","p":{"a":0,"k":[633.85,447.85]},"a":{"a":0,"k":[633.85,447.85]},"s":{"a":0,"k":[100,100]},"r":{"a":0,"k":0},"o":{"a":0,"k":100},"sk":{"a":0,"k":0},"sa":{"a":0,"k":0}}],"nm":"Object","hd":false},{"ty":"gr","it":[{"ty":"sh","d":1,"ks":{"a":0,"k":{"i":[[0,0],[-6.5,2.7],[0,0],[0,0]],"o":[[0,0],[6.5,-2.7],[0,0],[0,0]],"v":[[604.9,477.6],[615.6,477.6],[610,464.6],[604.9,477.6]],"c":true},"hd":false}},{"ty":"gf","t":1,"s":{"a":0,"k":[604.869,471.685]},"e":{"a":0,"k":[617.503,471.685]},"g":{"p":4,"k":{"a":0,"k":[0,0.271,0.192,0.58,0.279,0.294,0.212,0.6,0.636,0.353,0.271,0.659,1,0.447,0.353,0.749]}},"hd":false,"o":{"a":0,"k":100},"r":1},{"ty":"tr","p":{"a":0,"k":[611.209,471.7]},"a":{"a":0,"k":[611.209,471.7]},"s":{"a":0,"k":[100,100]},"r":{"a":0,"k":0},"o":{"a":0,"k":100},"sk":{"a":0,"k":0},"sa":{"a":0,"k":0}}],"nm":"Object","hd":false},{"ty":"gr","it":[{"ty":"sh","d":1,"ks":{"a":0,"k":{"i":[[0,0],[-2.9,-0.8],[0.2,-7.2],[0,0],[-1.7,5.5],[-34.5,10.6]],"o":[[2.9,-0.9],[11.2,3.1],[-0.1,4.2],[0,0],[1.6,-4.8],[0,0]],"v":[[605.5,404.7],[614.4,404.6],[657.5,421.6],[609.1,434.6],[567,420.6],[605.5,404.7]],"c":true},"hd":false}},{"ty":"gf","t":1,"s":{"a":0,"k":[582.678,416.33]},"e":{"a":0,"k":[657.44,424.473]},"g":{"p":3,"k":{"a":0,"k":[0,0.694,0.553,0.839,0.512,0.514,0.522,0.78,1,0.447,0.353,0.749]}},"hd":false,"o":{"a":0,"k":100},"r":1},{"ty":"tr","p":{"a":0,"k":[612.226,419.306]},"a":{"a":0,"k":[612.226,419.306]},"s":{"a":0,"k":[100,100]},"r":{"a":0,"k":0},"o":{"a":0,"k":100},"sk":{"a":0,"k":0},"sa":{"a":0,"k":0}}],"nm":"Object","hd":false},{"ty":"tr","p":{"a":0,"k":[612.25,441.406]},"a":{"a":0,"k":[612.25,441.406]},"s":{"a":0,"k":[100,100]},"r":{"a":0,"k":0},"o":{"a":0,"k":100},"sk":{"a":0,"k":0},"sa":{"a":0,"k":0}}],"nm":"Object","hd":false}],"ln":"Layer_2"},{"ind":4,"nm":"UPPR","ks":{"p":{"a":1,"k":[{"t":0,"s":[335.153,302.809,0],"to":[0,0,0],"ti":[0,0,0],"i":{"x":[0.58],"y":[1]},"o":{"x":[0.42],"y":[0]},"e":[335.153,285.309,0]},{"t":25,"s":[335.153,285.309,0],"to":[0,0,0],"ti":[0,0,0],"i":{"x":[0.58],"y":[1]},"o":{"x":[0.42],"y":[0]},"e":[335.153,302.809,0]},{"t":50,"s":[335.153,302.809,0],"to":[0,0,0],"ti":[0,0,0],"i":{"x":[0.58],"y":[1]},"o":{"x":[0.42],"y":[0]},"e":[335.153,285.309,0]},{"t":75,"s":[335.153,285.309,0],"to":[0,0,0],"ti":[0,0,0],"i":{"x":[0.58],"y":[1]},"o":{"x":[0.42],"y":[0]},"e":[335.153,302.809,0]},{"t":100,"s":[335.153,302.809,0]}]},"a":{"a":0,"k":[395.6,332.5,0]},"s":{"a":0,"k":[100,100,100]},"r":{"a":0,"k":0},"o":{"a":0,"k":100}},"ao":0,"ip":0,"op":100,"st":0,"bm":0,"sr":1,"ty":4,"shapes":[{"ty":"gr","it":[{"ty":"gr","it":[{"ty":"sh","d":1,"ks":{"a":0,"k":{"i":[[0,0],[0,0],[0,0],[0,0],[0,0]],"o":[[0,0],[0,0],[0,0],[0,0],[0,0]],"v":[[448.9,337.7],[448.9,337.7],[448.9,337.7],[448.9,337.7],[448.9,337.7]],"c":true},"hd":false}},{"ty":"sh","d":1,"ks":{"a":0,"k":{"i":[[0,0],[0.5,0.2],[0,0],[0.5,0.1],[0,0],[0,0],[0,0],[0,0],[0,0],[0.3,0.1],[0.5,0.2],[0,0],[0,0],[0,0],[0,0],[0,0],[0,0],[0,0],[0,0],[0,0],[0,0],[0,0],[0,0],[0,0],[0,0],[0,0],[0,0],[0,0],[0,0],[0,0],[0,0],[0,0],[0,0],[0,0],[0,0],[0,0],[0,0],[0,0],[0,0],[0,0],[0,0],[0,0],[0,0],[0,0],[0,0],[0,0],[0,0],[0,0],[0,0],[0,0],[0,0],[0,0],[0,0],[0,0],[0,0],[0,0],[0,0],[0,0],[0,0]],"o":[[-0.5,-0.2],[0,0],[-0.5,-0.2],[0,0],[0,0],[0,0],[0,0],[0,0],[-0.2,-0.1],[-0.5,-0.2],[0,0],[0,0],[0,0],[0,0],[0,0],[0,0],[0,0],[0,0],[0,0],[0,0],[0,0],[0,0],[0,0],[0,0],[0,0],[0,0],[0,0],[0,0],[0,0],[0,0],[0,0],[0,0],[0,0],[0,0],[0,0],[0,0],[0,0],[0,0],[0,0],[0,0],[0,0],[0,0],[0,0],[0,0],[0,0],[0,0],[0,0],[0,0],[0,0],[0,0],[0,0],[0,0],[0,0],[0,0],[0,0],[0,0],[0,0],[0,0],[0,0]],"v":[[501.5,286.6],[500,286.1],[500,286.1],[498.4,285.6],[498.4,285.6],[447.7,302.5],[398.9,286.2],[448.7,269.6],[448.5,269.1],[447.8,268.9],[446.2,268.4],[446.2,268.4],[395.7,285],[345.3,268.1],[343.4,268.7],[342.1,269.1],[392.5,286],[343.6,302.3],[293.2,285.4],[291.3,286.1],[290.2,286.5],[290.2,286.5],[290.2,286.6],[340.6,303.5],[289.9,320.4],[290.2,320.5],[290.2,320.5],[291.3,320.9],[291.3,320.9],[291.4,320.9],[291.5,320.9],[293,321.4],[293,321.4],[343.6,304.5],[392.3,320.9],[342.2,337.6],[342.3,337.8],[343.4,338.2],[344.2,338.5],[344.4,338.6],[345.1,338.8],[395.4,322],[445.6,338.9],[446.6,338.6],[446.7,338.6],[447.7,338.3],[448.8,337.9],[398.6,321.1],[447.6,304.8],[498,321.7],[499.6,321.2],[500,321.1],[500,321.1],[501.1,320.7],[501.1,320.7],[501.1,320.7],[501.1,320.7],[450.8,303.8],[501.5,286.6]],"c":true},"hd":false}},{"ty":"sh","d":1,"ks":{"a":0,"k":{"i":[[0,0],[0,0],[0,0],[0,0],[0,0]],"o":[[0,0],[0,0],[0,0],[0,0],[0,0]],"v":[[346.8,303.4],[395.7,287.1],[444.5,303.4],[395.5,319.7],[346.8,303.4]],"c":true},"hd":false}},{"ty":"gf","t":1,"s":{"a":0,"k":[515.04,301.307]},"e":{"a":0,"k":[312.599,304.871]},"g":{"p":5,"k":{"a":0,"k":[0,0.267,0.267,0.478,0.215,0.282,0.275,0.502,0.49,0.322,0.294,0.561,0.796,0.392,0.325,0.663,1,0.447,0.353,0.749]}},"hd":false,"o":{"a":0,"k":100},"r":1},{"ty":"tr","p":{"a":0,"k":[395.7,303.5]},"a":{"a":0,"k":[395.7,303.5]},"s":{"a":0,"k":[100,100]},"r":{"a":0,"k":0},"o":{"a":0,"k":100},"sk":{"a":0,"k":0},"sa":{"a":0,"k":0}}],"nm":"Object","hd":false},{"ty":"gr","it":[{"ty":"sh","d":1,"ks":{"a":0,"k":{"i":[[0,0],[0,0],[0,0],[0,0],[0,0],[0,0],[0,0],[0,0]],"o":[[0,0],[0,0],[0,0],[0,0],[0,0],[0,0],[0,0],[0,0]],"v":[[292.3,321.1],[292.3,379.3],[290.2,378.7],[290.2,320.3],[291.2,320.7],[291.3,320.7],[291.4,320.8],[291.5,320.8]],"c":true},"hd":false}},{"ty":"fl","c":{"a":0,"k":[0.502,0.322,0.6,1]},"hd":false,"o":{"a":0,"k":100},"r":1},{"ty":"tr","p":{"a":0,"k":[291.25,349.8]},"a":{"a":0,"k":[291.25,349.8]},"s":{"a":0,"k":[100,100]},"r":{"a":0,"k":0},"o":{"a":0,"k":100},"sk":{"a":0,"k":0},"sa":{"a":0,"k":0}}],"nm":"Object","hd":false},{"ty":"gr","it":[{"ty":"sh","d":1,"ks":{"a":0,"k":{"i":[[0,0],[0,0],[0,0],[0,0],[0,0],[0,0],[0,0],[0,0],[0,0],[0,0],[-17.4,-5.8]],"o":[[0,0],[0,0],[0,0],[0,0],[0,0],[0,0],[0,0],[0,0],[0,0],[17.3,5.7],[0,0]],"v":[[395.6,320.7],[343.5,338],[342.4,337.6],[342.4,337.6],[293,321.3],[293,321.3],[291.5,320.8],[291.4,320.8],[291.3,320.8],[343.5,303.5],[395.6,320.7]],"c":true},"hd":false}},{"ty":"gf","t":1,"s":{"a":0,"k":[276.28,328.069]},"e":{"a":0,"k":[349.824,320.007]},"g":{"p":2,"k":{"a":0,"k":[0,0.98,0.863,1,1,0.788,0.533,0.922,0,1,1,0]}},"hd":false,"o":{"a":0,"k":100},"r":1},{"ty":"tr","p":{"a":0,"k":[343.45,320.75]},"a":{"a":0,"k":[343.45,320.75]},"s":{"a":0,"k":[100,100]},"r":{"a":0,"k":0},"o":{"a":0,"k":100},"sk":{"a":0,"k":0},"sa":{"a":0,"k":0}}],"nm":"Object","hd":false},{"ty":"gr","it":[{"ty":"sh","d":1,"ks":{"a":0,"k":{"i":[[0,0],[0,0],[0,0],[0,0],[0,0],[0,0],[0,0],[0,0],[0,0],[0,0],[-17.4,-5.8]],"o":[[0,0],[0,0],[0,0],[0,0],[0,0],[0,0],[0,0],[0,0],[0,0],[17.3,5.7],[0,0]],"v":[[395.6,320.7],[343.5,338],[342.4,337.6],[342.4,337.6],[293,321.3],[293,321.3],[291.5,320.8],[291.4,320.8],[291.3,320.8],[343.5,303.5],[395.6,320.7]],"c":true},"hd":false}},{"ty":"gf","t":1,"s":{"a":0,"k":[287.874,350.299]},"e":{"a":0,"k":[485.378,245.097]},"g":{"p":3,"k":{"a":0,"k":[0,0.694,0.553,0.839,0.512,0.514,0.541,0.859,1,0.447,0.353,0.749]}},"hd":false,"o":{"a":0,"k":100},"r":1},{"ty":"tr","p":{"a":0,"k":[343.45,320.75]},"a":{"a":0,"k":[343.45,320.75]},"s":{"a":0,"k":[100,100]},"r":{"a":0,"k":0},"o":{"a":0,"k":100},"sk":{"a":0,"k":0},"sa":{"a":0,"k":0}}],"nm":"Object","hd":false},{"ty":"gr","it":[{"ty":"sh","d":1,"ks":{"a":0,"k":{"i":[[0,0],[0,0],[0,0],[0,0],[0,0],[0,0],[0,0],[0,0],[0,0],[0,0],[0,0],[0,0],[-17.4,-5.7]],"o":[[0,0],[0,0],[0,0],[0,0],[0,0],[0,0],[0,0],[0,0],[0,0],[0,0],[0,0],[17.5,5.9],[0,0]],"v":[[447.8,338],[446.8,338.3],[446.7,338.3],[445.7,338.6],[395.6,355.3],[395.6,355.3],[345.1,338.5],[344.4,338.3],[344.2,338.2],[343.4,337.9],[395.5,320.6],[395.5,320.6],[447.8,338]],"c":true},"hd":false}},{"ty":"gf","t":1,"s":{"a":0,"k":[334.804,343.527]},"e":{"a":0,"k":[392.186,338.35]},"g":{"p":2,"k":{"a":0,"k":[0,0.98,0.863,1,1,0.788,0.533,0.922,0,1,1,0]}},"hd":false,"o":{"a":0,"k":100},"r":1},{"ty":"tr","p":{"a":0,"k":[395.6,337.95]},"a":{"a":0,"k":[395.6,337.95]},"s":{"a":0,"k":[100,100]},"r":{"a":0,"k":0},"o":{"a":0,"k":100},"sk":{"a":0,"k":0},"sa":{"a":0,"k":0}}],"nm":"Object","hd":false},{"ty":"gr","it":[{"ty":"sh","d":1,"ks":{"a":0,"k":{"i":[[0,0],[0,0],[0,0],[0,0],[0,0],[0,0],[0,0],[0,0],[0,0],[0,0],[0,0],[0,0],[-17.4,-5.7]],"o":[[0,0],[0,0],[0,0],[0,0],[0,0],[0,0],[0,0],[0,0],[0,0],[0,0],[0,0],[17.5,5.9],[0,0]],"v":[[447.8,338],[446.8,338.3],[446.7,338.3],[445.7,338.6],[395.6,355.3],[395.6,355.3],[345.1,338.5],[344.4,338.3],[344.2,338.2],[343.4,337.9],[395.5,320.6],[395.5,320.6],[447.8,338]],"c":true},"hd":false}},{"ty":"gf","t":1,"s":{"a":0,"k":[306.595,385.445]},"e":{"a":0,"k":[504.098,280.242]},"g":{"p":3,"k":{"a":0,"k":[0,0.694,0.553,0.839,0.512,0.514,0.541,0.859,1,0.447,0.353,0.749]}},"hd":false,"o":{"a":0,"k":100},"r":1},{"ty":"tr","p":{"a":0,"k":[395.6,337.95]},"a":{"a":0,"k":[395.6,337.95]},"s":{"a":0,"k":[100,100]},"r":{"a":0,"k":0},"o":{"a":0,"k":100},"sk":{"a":0,"k":0},"sa":{"a":0,"k":0}}],"nm":"Object","hd":false},{"ty":"gr","it":[{"ty":"sh","d":1,"ks":{"a":0,"k":{"i":[[0,0],[0,0],[0,0],[0,0],[0,0],[0,0],[0,0],[0,0]],"o":[[0,0],[0,0],[0,0],[0,0],[0,0],[0,0],[0,0],[0,0]],"v":[[344.5,338.4],[344.5,396.7],[343.4,396.3],[343.2,396.2],[342.4,396],[342.4,337.6],[343.5,338],[344.3,338.3]],"c":true},"hd":false}},{"ty":"fl","c":{"a":0,"k":[0.502,0.322,0.6,1]},"hd":false,"o":{"a":0,"k":100},"r":1},{"ty":"tr","p":{"a":0,"k":[343.45,367.15]},"a":{"a":0,"k":[343.45,367.15]},"s":{"a":0,"k":[100,100]},"r":{"a":0,"k":0},"o":{"a":0,"k":100},"sk":{"a":0,"k":0},"sa":{"a":0,"k":0}}],"nm":"Object","hd":false},{"ty":"gr","it":[{"ty":"sh","d":1,"ks":{"a":0,"k":{"i":[[0,0],[0,0],[0,0],[0,0],[0,0],[0,0],[0,0]],"o":[[0,0],[0,0],[0,0],[0,0],[0,0],[0,0],[0,0]],"v":[[501.1,320.3],[501.1,378.7],[498.9,379.3],[498.9,321.1],[499.6,320.9],[500,320.7],[500,320.7]],"c":true},"hd":false}},{"ty":"fl","c":{"a":0,"k":[0.176,0.141,0.31,1]},"hd":false,"o":{"a":0,"k":100},"r":1},{"ty":"tr","p":{"a":0,"k":[500,349.8]},"a":{"a":0,"k":[500,349.8]},"s":{"a":0,"k":[100,100]},"r":{"a":0,"k":0},"o":{"a":0,"k":100},"sk":{"a":0,"k":0},"sa":{"a":0,"k":0}}],"nm":"Object","hd":false},{"ty":"gr","it":[{"ty":"sh","d":1,"ks":{"a":0,"k":{"i":[[0,0],[0,0],[0,0],[0,0],[0,0],[0,0],[0,0],[0,0],[17.4,5.8],[0,0],[0,0],[-17.4,-5.8]],"o":[[0,0],[0,0],[0,0],[0,0],[0,0],[0,0],[0,0],[-17.4,-5.8],[0,0],[0,0],[17.4,5.8],[0,0]],"v":[[500,320.7],[499.6,320.8],[498,321.3],[448.9,337.6],[448.9,337.6],[448.9,337.6],[448.9,337.6],[447.8,338],[395.6,320.7],[447.8,303.4],[447.8,303.4],[500,320.7]],"c":true},"hd":false}},{"ty":"gf","t":1,"s":{"a":0,"k":[310.941,393.604]},"e":{"a":0,"k":[508.444,288.401]},"g":{"p":3,"k":{"a":0,"k":[0,0.694,0.553,0.839,0.512,0.514,0.541,0.859,1,0.447,0.353,0.749]}},"hd":false,"o":{"a":0,"k":100},"r":1},{"ty":"tr","p":{"a":0,"k":[447.8,320.7]},"a":{"a":0,"k":[447.8,320.7]},"s":{"a":0,"k":[100,100]},"r":{"a":0,"k":0},"o":{"a":0,"k":100},"sk":{"a":0,"k":0},"sa":{"a":0,"k":0}}],"nm":"Object","hd":false},{"ty":"gr","it":[{"ty":"sh","d":1,"ks":{"a":0,"k":{"i":[[0,0],[0,0],[0,0],[17.4,5.8],[0,0],[-17.4,-5.8]],"o":[[0,0],[0,0],[-17.4,-5.8],[0,0],[17.4,5.7],[0,0]],"v":[[447.8,303.4],[395.6,320.7],[395.6,320.7],[343.4,303.4],[395.6,286.1],[447.8,303.4]],"c":true},"hd":false}},{"ty":"gf","t":1,"s":{"a":0,"k":[321.88,315.539]},"e":{"a":0,"k":[404.589,301.901]},"g":{"p":2,"k":{"a":0,"k":[0,0.98,0.863,1,1,0.788,0.533,0.922,0,1,1,0]}},"hd":false,"o":{"a":0,"k":100},"r":1},{"ty":"tr","p":{"a":0,"k":[395.6,303.4]},"a":{"a":0,"k":[395.6,303.4]},"s":{"a":0,"k":[100,100]},"r":{"a":0,"k":0},"o":{"a":0,"k":100},"sk":{"a":0,"k":0},"sa":{"a":0,"k":0}}],"nm":"Object","hd":false},{"ty":"gr","it":[{"ty":"sh","d":1,"ks":{"a":0,"k":{"i":[[0,0],[0,0],[0,0],[17.4,5.8],[0,0],[-17.4,-5.8]],"o":[[0,0],[0,0],[-17.4,-5.8],[0,0],[17.4,5.7],[0,0]],"v":[[447.8,303.4],[395.6,320.7],[395.6,320.7],[343.4,303.4],[395.6,286.1],[447.8,303.4]],"c":true},"hd":false}},{"ty":"gf","t":1,"s":{"a":0,"k":[292.219,358.457]},"e":{"a":0,"k":[489.723,253.254]},"g":{"p":3,"k":{"a":0,"k":[0,0.694,0.553,0.839,0.512,0.514,0.541,0.859,1,0.447,0.353,0.749]}},"hd":false,"o":{"a":0,"k":100},"r":1},{"ty":"tr","p":{"a":0,"k":[395.6,303.4]},"a":{"a":0,"k":[395.6,303.4]},"s":{"a":0,"k":[100,100]},"r":{"a":0,"k":0},"o":{"a":0,"k":100},"sk":{"a":0,"k":0},"sa":{"a":0,"k":0}}],"nm":"Object","hd":false},{"ty":"gr","it":[{"ty":"sh","d":1,"ks":{"a":0,"k":{"i":[[0,0],[0,0],[0,0],[0,0],[0,0],[0,0],[0,0],[0,0],[0,0],[0,0]],"o":[[0,0],[0,0],[0,0],[0,0],[0,0],[0,0],[0,0],[0,0],[0,0],[0,0]],"v":[[448.9,337.6],[448.9,396],[448.2,396.2],[448.2,396.2],[448,396.3],[447.8,396.3],[446.7,396.7],[446.7,338.4],[446.8,338.4],[447.8,338]],"c":true},"hd":false}},{"ty":"fl","c":{"a":0,"k":[0.176,0.141,0.31,1]},"hd":false,"o":{"a":0,"k":100},"r":1},{"ty":"tr","p":{"a":0,"k":[447.8,367.15]},"a":{"a":0,"k":[447.8,367.15]},"s":{"a":0,"k":[100,100]},"r":{"a":0,"k":0},"o":{"a":0,"k":100},"sk":{"a":0,"k":0},"sa":{"a":0,"k":0}}],"nm":"Object","hd":false},{"ty":"gr","it":[{"ty":"sh","d":1,"ks":{"a":0,"k":{"i":[[0,0],[0,0],[0,0],[0,0],[0,0],[0,0],[17.4,5.7],[0,0],[0,0],[-0.5,-0.2],[0,0],[0,0]],"o":[[0,0],[0,0],[0,0],[0,0],[0,0],[-17.4,-5.8],[0,0],[0,0],[0.5,0.2],[0,0],[0,0],[0,0]],"v":[[552.2,303.4],[501.1,320.4],[501.1,320.4],[501.1,320.4],[500,320.8],[500,320.8],[447.8,303.5],[500,286],[500,286],[501.5,286.5],[501.5,286.5],[552.2,303.4]],"c":true},"hd":false}},{"ty":"gf","t":1,"s":{"a":0,"k":[315.289,401.768]},"e":{"a":0,"k":[512.793,296.565]},"g":{"p":3,"k":{"a":0,"k":[0,0.694,0.553,0.839,0.512,0.514,0.541,0.859,1,0.447,0.353,0.749]}},"hd":false,"o":{"a":0,"k":100},"r":1},{"ty":"tr","p":{"a":0,"k":[500,303.4]},"a":{"a":0,"k":[500,303.4]},"s":{"a":0,"k":[100,100]},"r":{"a":0,"k":0},"o":{"a":0,"k":100},"sk":{"a":0,"k":0},"sa":{"a":0,"k":0}}],"nm":"Object","hd":false},{"ty":"gr","it":[{"ty":"sh","d":1,"ks":{"a":0,"k":{"i":[[0,0],[0,0],[0,0],[17.4,5.8],[0,0],[-0.3,0],[-16.7,-5.6],[0,0],[-0.5,-0.1]],"o":[[0,0],[0,0],[-17.4,-5.8],[0,0],[0.2,0.1],[16.6,5.5],[0,0],[0.5,0.2],[0,0]],"v":[[500,286],[447.8,303.3],[447.8,303.3],[395.6,286],[447.8,268.7],[448.5,268.9],[498.4,285.5],[498.4,285.5],[500,286]],"c":true},"hd":false}},{"ty":"gf","t":1,"s":{"a":0,"k":[296.563,366.611]},"e":{"a":0,"k":[494.066,261.408]},"g":{"p":3,"k":{"a":0,"k":[0,0.694,0.553,0.839,0.512,0.514,0.541,0.859,1,0.447,0.353,0.749]}},"hd":false,"o":{"a":0,"k":100},"r":1},{"ty":"tr","p":{"a":0,"k":[447.8,286]},"a":{"a":0,"k":[447.8,286]},"s":{"a":0,"k":[100,100]},"r":{"a":0,"k":0},"o":{"a":0,"k":100},"sk":{"a":0,"k":0},"sa":{"a":0,"k":0}}],"nm":"Object","hd":false},{"ty":"gr","it":[{"ty":"sh","d":1,"ks":{"a":0,"k":{"i":[[0,0],[0,0],[17.4,5.7],[0,0],[0,0],[-16.9,-5.6],[0,0],[-0.5,-0.2]],"o":[[0,0],[-17.4,-5.8],[0,0],[0,0],[16.9,5.6],[0,0],[0.6,0.2],[0,0]],"v":[[447.8,268.7],[395.6,286],[343.4,268.7],[345.3,268.1],[395.6,251.4],[446.2,268.2],[446.2,268.2],[447.8,268.7]],"c":true},"hd":false}},{"ty":"gf","t":1,"s":{"a":0,"k":[331.59,278.577]},"e":{"a":0,"k":[394.108,268.959]},"g":{"p":2,"k":{"a":0,"k":[0,0.98,0.863,1,1,0.788,0.533,0.922,0,1,1,0]}},"hd":false,"o":{"a":0,"k":100},"r":1},{"ty":"tr","p":{"a":0,"k":[395.6,268.7]},"a":{"a":0,"k":[395.6,268.7]},"s":{"a":0,"k":[100,100]},"r":{"a":0,"k":0},"o":{"a":0,"k":100},"sk":{"a":0,"k":0},"sa":{"a":0,"k":0}}],"nm":"Object","hd":false},{"ty":"gr","it":[{"ty":"sh","d":1,"ks":{"a":0,"k":{"i":[[0,0],[0,0],[17.4,5.7],[0,0],[0,0],[-16.9,-5.6],[0,0],[-0.5,-0.2]],"o":[[0,0],[-17.4,-5.8],[0,0],[0,0],[16.9,5.6],[0,0],[0.6,0.2],[0,0]],"v":[[447.8,268.7],[395.6,286],[343.4,268.7],[345.3,268.1],[395.6,251.4],[446.2,268.2],[446.2,268.2],[447.8,268.7]],"c":true},"hd":false}},{"ty":"gf","t":1,"s":{"a":0,"k":[277.84,331.462]},"e":{"a":0,"k":[475.343,226.259]},"g":{"p":3,"k":{"a":0,"k":[0,0.694,0.553,0.839,0.512,0.514,0.541,0.859,1,0.447,0.353,0.749]}},"hd":false,"o":{"a":0,"k":100},"r":1},{"ty":"tr","p":{"a":0,"k":[395.6,268.7]},"a":{"a":0,"k":[395.6,268.7]},"s":{"a":0,"k":[100,100]},"r":{"a":0,"k":0},"o":{"a":0,"k":100},"sk":{"a":0,"k":0},"sa":{"a":0,"k":0}}],"nm":"Object","hd":false},{"ty":"gr","it":[{"ty":"sh","d":1,"ks":{"a":0,"k":{"i":[[0,0],[0,0],[0,0],[0,0],[0,0],[0,0],[0,0],[0,0],[0,0],[0,0],[-17.4,-5.8]],"o":[[0,0],[0,0],[0,0],[0,0],[0,0],[0,0],[0,0],[0,0],[0,0],[17.4,5.9],[0,0]],"v":[[343.4,303.4],[291.2,320.7],[291.2,320.7],[290.1,320.3],[290.1,320.3],[289.8,320.2],[239,303.3],[290.1,286.3],[290.1,286.3],[291.2,285.9],[343.4,303.4]],"c":true},"hd":false}},{"ty":"gf","t":1,"s":{"a":0,"k":[243.097,301.052]},"e":{"a":0,"k":[309.821,304.287]},"g":{"p":2,"k":{"a":0,"k":[0,0.98,0.863,1,1,0.788,0.533,0.922,0,1,1,0]}},"hd":false,"o":{"a":0,"k":100},"r":1},{"ty":"tr","p":{"a":0,"k":[291.2,303.3]},"a":{"a":0,"k":[291.2,303.3]},"s":{"a":0,"k":[100,100]},"r":{"a":0,"k":0},"o":{"a":0,"k":100},"sk":{"a":0,"k":0},"sa":{"a":0,"k":0}}],"nm":"Object","hd":false},{"ty":"gr","it":[{"ty":"sh","d":1,"ks":{"a":0,"k":{"i":[[0,0],[0,0],[0,0],[0,0],[0,0],[0,0],[0,0],[0,0],[0,0],[0,0],[-17.4,-5.8]],"o":[[0,0],[0,0],[0,0],[0,0],[0,0],[0,0],[0,0],[0,0],[0,0],[17.4,5.9],[0,0]],"v":[[343.4,303.4],[291.2,320.7],[291.2,320.7],[290.1,320.3],[290.1,320.3],[289.8,320.2],[239,303.3],[290.1,286.3],[290.1,286.3],[291.2,285.9],[343.4,303.4]],"c":true},"hd":false}},{"ty":"gf","t":1,"s":{"a":0,"k":[269.154,315.155]},"e":{"a":0,"k":[466.657,209.952]},"g":{"p":3,"k":{"a":0,"k":[0,0.694,0.553,0.839,0.512,0.514,0.541,0.859,1,0.447,0.353,0.749]}},"hd":false,"o":{"a":0,"k":100},"r":1},{"ty":"tr","p":{"a":0,"k":[291.2,303.3]},"a":{"a":0,"k":[291.2,303.3]},"s":{"a":0,"k":[100,100]},"r":{"a":0,"k":0},"o":{"a":0,"k":100},"sk":{"a":0,"k":0},"sa":{"a":0,"k":0}}],"nm":"Object","hd":false},{"ty":"gr","it":[{"ty":"sh","d":1,"ks":{"a":0,"k":{"i":[[0,0],[0,0],[17.4,5.8],[0,0],[0,0],[0,0],[-17.4,-5.8]],"o":[[0,0],[-17.4,-5.8],[0,0],[0,0],[0,0],[17.5,5.7],[0,0]],"v":[[395.6,286.1],[343.4,303.4],[291.2,286.1],[293.1,285.4],[342,269.2],[343.3,268.8],[395.6,286.1]],"c":true},"hd":false}},{"ty":"gf","t":1,"s":{"a":0,"k":[280.614,288.733]},"e":{"a":0,"k":[351.594,285.709]},"g":{"p":2,"k":{"a":0,"k":[0,0.98,0.863,1,1,0.788,0.533,0.922,0,1,1,0]}},"hd":false,"o":{"a":0,"k":100},"r":1},{"ty":"tr","p":{"a":0,"k":[343.4,286.1]},"a":{"a":0,"k":[343.4,286.1]},"s":{"a":0,"k":[100,100]},"r":{"a":0,"k":0},"o":{"a":0,"k":100},"sk":{"a":0,"k":0},"sa":{"a":0,"k":0}}],"nm":"Object","hd":false},{"ty":"gr","it":[{"ty":"sh","d":1,"ks":{"a":0,"k":{"i":[[0,0],[0,0],[17.4,5.8],[0,0],[0,0],[0,0],[-17.4,-5.8]],"o":[[0,0],[-17.4,-5.8],[0,0],[0,0],[0,0],[17.5,5.7],[0,0]],"v":[[395.6,286.1],[343.4,303.4],[291.2,286.1],[293.1,285.4],[342,269.2],[343.3,268.8],[395.6,286.1]],"c":true},"hd":false}},{"ty":"gf","t":1,"s":{"a":0,"k":[273.498,323.31]},"e":{"a":0,"k":[471.001,218.107]},"g":{"p":3,"k":{"a":0,"k":[0,0.694,0.553,0.839,0.512,0.514,0.541,0.859,1,0.447,0.353,0.749]}},"hd":false,"o":{"a":0,"k":100},"r":1},{"ty":"tr","p":{"a":0,"k":[343.4,286.1]},"a":{"a":0,"k":[343.4,286.1]},"s":{"a":0,"k":[100,100]},"r":{"a":0,"k":0},"o":{"a":0,"k":100},"sk":{"a":0,"k":0},"sa":{"a":0,"k":0}}],"nm":"Object","hd":false},{"ty":"gr","it":[{"ty":"sh","d":1,"ks":{"a":0,"k":{"i":[[0,0],[0,0]],"o":[[0,0],[0,0]],"v":[[343.5,338],[343.4,338]],"c":false},"hd":false}},{"ty":"st","c":{"a":0,"k":[0,0,0,1]},"o":{"a":0,"k":100},"w":{"a":0,"k":1},"lc":2,"lj":2,"ml":10},{"ty":"tr","p":{"a":0,"k":[343.45,338]},"a":{"a":0,"k":[343.45,338]},"s":{"a":0,"k":[100,100]},"r":{"a":0,"k":0},"o":{"a":0,"k":100},"sk":{"a":0,"k":0},"sa":{"a":0,"k":0}}],"nm":"Object","hd":false},{"ty":"gr","it":[{"ty":"sh","d":1,"ks":{"a":0,"k":{"i":[[0,0],[0,0],[0,0],[0,0],[0,0],[0,0],[0,0],[0,0]],"o":[[0,0],[0,0],[0,0],[0,0],[0,0],[0,0],[0,0],[0,0]],"v":[[291.3,320.7],[291.3,379],[290.2,378.6],[257,367.6],[239.1,361.6],[239.1,303.4],[290.2,320.4],[291.2,320.7]],"c":true},"hd":false}},{"ty":"gf","t":1,"s":{"a":0,"k":[231.389,336.189]},"e":{"a":0,"k":[258.27,340.171]},"g":{"p":2,"k":{"a":0,"k":[0,0.98,0.863,1,1,0.788,0.533,0.922,0,1,1,0]}},"hd":false,"o":{"a":0,"k":100},"r":1},{"ty":"tr","p":{"a":0,"k":[265.2,341.2]},"a":{"a":0,"k":[265.2,341.2]},"s":{"a":0,"k":[100,100]},"r":{"a":0,"k":0},"o":{"a":0,"k":100},"sk":{"a":0,"k":0},"sa":{"a":0,"k":0}}],"nm":"Object","hd":false},{"ty":"gr","it":[{"ty":"sh","d":1,"ks":{"a":0,"k":{"i":[[0,0],[0,0],[0,0],[0,0],[0,0],[0,0],[0,0],[0,0]],"o":[[0,0],[0,0],[0,0],[0,0],[0,0],[0,0],[0,0],[0,0]],"v":[[291.3,320.7],[291.3,379],[290.2,378.6],[257,367.6],[239.1,361.6],[239.1,303.4],[290.2,320.4],[291.2,320.7]],"c":true},"hd":false}},{"ty":"gf","t":1,"s":{"a":0,"k":[241.06,315.434]},"e":{"a":0,"k":[619.633,719.949]},"g":{"p":5,"k":{"a":0,"k":[0,0.918,0.471,0.78,0.196,0.702,0.408,0.761,0.368,0.541,0.365,0.749,0.502,0.439,0.337,0.741,0.584,0.404,0.325,0.737]}},"hd":false,"o":{"a":0,"k":100},"r":1},{"ty":"tr","p":{"a":0,"k":[265.2,341.2]},"a":{"a":0,"k":[265.2,341.2]},"s":{"a":0,"k":[100,100]},"r":{"a":0,"k":0},"o":{"a":0,"k":100},"sk":{"a":0,"k":0},"sa":{"a":0,"k":0}}],"nm":"Object","hd":false},{"ty":"gr","it":[{"ty":"sh","d":1,"ks":{"a":0,"k":{"i":[[0,0],[0,0],[0,0],[0,0],[0,0],[0,0],[0,0]],"o":[[0,0],[0,0],[0,0],[0,0],[0,0],[0,0],[0,0]],"v":[[395.6,355.4],[395.6,413.6],[344.5,396.7],[343.4,396.3],[343.4,338],[344.3,338.3],[344.5,338.4]],"c":true},"hd":false}},{"ty":"gf","t":1,"s":{"a":0,"k":[337.73,377.368]},"e":{"a":0,"k":[365.622,376.029]},"g":{"p":2,"k":{"a":0,"k":[0,0.98,0.863,1,1,0.788,0.533,0.922,0,1,1,0]}},"hd":false,"o":{"a":0,"k":100},"r":1},{"ty":"tr","p":{"a":0,"k":[369.5,375.8]},"a":{"a":0,"k":[369.5,375.8]},"s":{"a":0,"k":[100,100]},"r":{"a":0,"k":0},"o":{"a":0,"k":100},"sk":{"a":0,"k":0},"sa":{"a":0,"k":0}}],"nm":"Object","hd":false},{"ty":"gr","it":[{"ty":"sh","d":1,"ks":{"a":0,"k":{"i":[[0,0],[0,0],[0,0],[0,0],[0,0],[0,0],[0,0]],"o":[[0,0],[0,0],[0,0],[0,0],[0,0],[0,0],[0,0]],"v":[[395.6,355.4],[395.6,413.6],[344.5,396.7],[343.4,396.3],[343.4,338],[344.3,338.3],[344.5,338.4]],"c":true},"hd":false}},{"ty":"gf","t":1,"s":{"a":0,"k":[279.405,279.538]},"e":{"a":0,"k":[657.978,684.055]},"g":{"p":5,"k":{"a":0,"k":[0,0.918,0.471,0.78,0.196,0.702,0.408,0.761,0.368,0.541,0.365,0.749,0.502,0.439,0.337,0.741,0.584,0.404,0.325,0.737]}},"hd":false,"o":{"a":0,"k":100},"r":1},{"ty":"tr","p":{"a":0,"k":[369.5,375.8]},"a":{"a":0,"k":[369.5,375.8]},"s":{"a":0,"k":[100,100]},"r":{"a":0,"k":0},"o":{"a":0,"k":100},"sk":{"a":0,"k":0},"sa":{"a":0,"k":0}}],"nm":"Object","hd":false},{"ty":"gr","it":[{"ty":"sh","d":1,"ks":{"a":0,"k":{"i":[[0,0],[0,0],[0,0],[0,0],[0,0],[0,0],[0,0],[0,0],[0,0],[0,0]],"o":[[0,0],[0,0],[0,0],[0,0],[0,0],[0,0],[0,0],[0,0],[0,0],[0,0]],"v":[[343.4,338],[343.4,396.3],[343.2,396.2],[342.4,396],[292.3,379.3],[291.3,379],[291.3,320.7],[291.4,320.8],[291.5,320.8],[342.4,337.7]],"c":true},"hd":false}},{"ty":"gf","t":1,"s":{"a":0,"k":[282.009,355.434]},"e":{"a":0,"k":[307.583,357.669]},"g":{"p":2,"k":{"a":0,"k":[0,0.98,0.863,1,1,0.788,0.533,0.922,0,1,1,0]}},"hd":false,"o":{"a":0,"k":100},"r":1},{"ty":"tr","p":{"a":0,"k":[317.35,358.5]},"a":{"a":0,"k":[317.35,358.5]},"s":{"a":0,"k":[100,100]},"r":{"a":0,"k":0},"o":{"a":0,"k":100},"sk":{"a":0,"k":0},"sa":{"a":0,"k":0}}],"nm":"Object","hd":false},{"ty":"gr","it":[{"ty":"sh","d":1,"ks":{"a":0,"k":{"i":[[0,0],[0,0],[0,0],[0,0],[0,0],[0,0],[0,0],[0,0],[0,0],[0,0]],"o":[[0,0],[0,0],[0,0],[0,0],[0,0],[0,0],[0,0],[0,0],[0,0],[0,0]],"v":[[343.4,338],[343.4,396.3],[343.2,396.2],[342.4,396],[292.3,379.3],[291.3,379],[291.3,320.7],[291.4,320.8],[291.5,320.8],[342.4,337.7]],"c":true},"hd":false}},{"ty":"gf","t":1,"s":{"a":0,"k":[260.236,297.492]},"e":{"a":0,"k":[638.781,701.977]},"g":{"p":5,"k":{"a":0,"k":[0,0.918,0.471,0.78,0.196,0.702,0.408,0.761,0.368,0.541,0.365,0.749,0.502,0.439,0.337,0.741,0.584,0.404,0.325,0.737]}},"hd":false,"o":{"a":0,"k":100},"r":1},{"ty":"tr","p":{"a":0,"k":[317.35,358.5]},"a":{"a":0,"k":[317.35,358.5]},"s":{"a":0,"k":[100,100]},"r":{"a":0,"k":0},"o":{"a":0,"k":100},"sk":{"a":0,"k":0},"sa":{"a":0,"k":0}}],"nm":"Object","hd":false},{"ty":"gr","it":[{"ty":"sh","d":1,"ks":{"a":0,"k":{"i":[[0,0],[0,0],[0,0],[0,0],[0,0],[0,0]],"o":[[0,0],[0,0],[0,0],[0,0],[0,0],[0,0]],"v":[[552.2,303.4],[552.2,361.6],[501.1,378.6],[500,379],[500,320.7],[501.1,320.4]],"c":true},"hd":false}},{"ty":"gf","t":1,"s":{"a":0,"k":[499.992,341.191]},"e":{"a":0,"k":[552.182,341.191]},"g":{"p":4,"k":{"a":0,"k":[0,0.447,0.353,0.749,0.364,0.353,0.271,0.659,0.721,0.294,0.212,0.6,1,0.271,0.192,0.58]}},"hd":false,"o":{"a":0,"k":100},"r":1},{"ty":"tr","p":{"a":0,"k":[526.1,341.2]},"a":{"a":0,"k":[526.1,341.2]},"s":{"a":0,"k":[100,100]},"r":{"a":0,"k":0},"o":{"a":0,"k":100},"sk":{"a":0,"k":0},"sa":{"a":0,"k":0}}],"nm":"Object","hd":false},{"ty":"gr","it":[{"ty":"sh","d":1,"ks":{"a":0,"k":{"i":[[0,0],[0,0],[0,0],[0,0],[0,0],[0,0],[0,0],[0,0]],"o":[[0,0],[0,0],[0,0],[0,0],[0,0],[0,0],[0,0],[0,0]],"v":[[447.8,338],[447.8,396.3],[446.7,396.7],[395.6,413.6],[395.6,355.4],[446.7,338.4],[446.8,338.4],[447.8,338]],"c":true},"hd":false}},{"ty":"gf","t":1,"s":{"a":0,"k":[395.622,375.841]},"e":{"a":0,"k":[447.802,375.841]},"g":{"p":4,"k":{"a":0,"k":[0,0.447,0.353,0.749,0.364,0.353,0.271,0.659,0.721,0.294,0.212,0.6,1,0.271,0.192,0.58]}},"hd":false,"o":{"a":0,"k":100},"r":1},{"ty":"tr","p":{"a":0,"k":[421.7,375.8]},"a":{"a":0,"k":[421.7,375.8]},"s":{"a":0,"k":[100,100]},"r":{"a":0,"k":0},"o":{"a":0,"k":100},"sk":{"a":0,"k":0},"sa":{"a":0,"k":0}}],"nm":"Object","hd":false},{"ty":"gr","it":[{"ty":"sh","d":1,"ks":{"a":0,"k":{"i":[[0,0],[0,0],[0,0],[0,0],[0,0],[0,0],[0,0],[0,0],[0,0],[0,0],[0,0],[0,0]],"o":[[0,0],[0,0],[0,0],[0,0],[0,0],[0,0],[0,0],[0,0],[0,0],[0,0],[0,0],[0,0]],"v":[[500,320.7],[500,379],[498.9,379.3],[498.9,379.3],[448.9,396],[448.2,396.2],[448.2,396.2],[447.8,396.3],[447.8,338],[448.9,337.7],[499.6,320.9],[500,320.7]],"c":true},"hd":false}},{"ty":"gf","t":1,"s":{"a":0,"k":[447.802,358.521]},"e":{"a":0,"k":[499.992,358.521]},"g":{"p":4,"k":{"a":0,"k":[0,0.447,0.353,0.749,0.364,0.353,0.271,0.659,0.721,0.294,0.212,0.6,1,0.271,0.192,0.58]}},"hd":false,"o":{"a":0,"k":100},"r":1},{"ty":"tr","p":{"a":0,"k":[473.9,358.5]},"a":{"a":0,"k":[473.9,358.5]},"s":{"a":0,"k":[100,100]},"r":{"a":0,"k":0},"o":{"a":0,"k":100},"sk":{"a":0,"k":0},"sa":{"a":0,"k":0}}],"nm":"Object","hd":false},{"ty":"tr","p":{"a":0,"k":[395.6,332.5]},"a":{"a":0,"k":[395.6,332.5]},"s":{"a":0,"k":[100,100]},"r":{"a":0,"k":0},"o":{"a":0,"k":100},"sk":{"a":0,"k":0},"sa":{"a":0,"k":0}}],"nm":"Object","hd":false}],"ln":"UPPR"},{"ind":3,"nm":"MID","ks":{"p":{"a":0,"k":[335.203,374.009]},"a":{"a":0,"k":[395.65,403.7,0]},"s":{"a":0,"k":[100,100,100]},"r":{"a":0,"k":0},"o":{"a":0,"k":100}},"ao":0,"ip":0,"op":100,"st":0,"bm":0,"sr":1,"ty":4,"shapes":[{"ty":"gr","it":[{"ty":"gr","it":[{"d":1,"ty":"rc","s":{"a":0,"k":[2.7,7]},"p":{"a":0,"k":[1.35,3.5]},"r":{"a":0,"k":0}},{"ty":"fl","c":{"a":0,"k":[0.212,0.212,0.408,1]},"hd":false,"o":{"a":0,"k":100},"r":1},{"ty":"tr","p":{"a":0,"k":[362.15,404]},"a":{"a":0,"k":[1.35,3.5]},"s":{"a":0,"k":[100,100]},"r":{"a":0,"k":0},"o":{"a":0,"k":100},"sk":{"a":0,"k":0},"sa":{"a":0,"k":0}}],"nm":"Object","hd":false},{"ty":"gr","it":[{"d":1,"ty":"rc","s":{"a":0,"k":[64.3,59.7]},"p":{"a":0,"k":[32.15,29.85]},"r":{"a":0,"k":0}},{"ty":"gf","t":1,"s":{"a":0,"k":[-5.749,78.306]},"e":{"a":0,"k":[33.974,27.513]},"g":{"p":2,"k":{"a":0,"k":[0,1,0.529,0.878,1,0.788,0.533,0.922,0,0.7,1,0]}},"hd":false,"o":{"a":0,"k":100},"r":1},{"ty":"tr","p":{"a":0,"k":[331.35,377.65]},"a":{"a":0,"k":[32.15,29.85]},"s":{"a":0,"k":[100,100]},"r":{"a":0,"k":0},"o":{"a":0,"k":100},"sk":{"a":0,"k":0},"sa":{"a":0,"k":0}}],"nm":"Object","hd":false},{"ty":"gr","it":[{"d":1,"ty":"rc","s":{"a":0,"k":[64.3,59.7]},"p":{"a":0,"k":[32.15,29.85]},"r":{"a":0,"k":0}},{"ty":"gf","t":1,"s":{"a":0,"k":[26.037,98.608]},"e":{"a":0,"k":[35.968,-13.019]},"g":{"p":8,"k":{"a":0,"k":[0,0.624,0.631,0.878,0.282,0.447,0.353,0.749,0.307,0.42,0.333,0.702,0.399,0.333,0.271,0.549,0.49,0.267,0.22,0.427,0.578,0.216,0.184,0.341,0.663,0.188,0.165,0.29,0.739,0.176,0.157,0.271]}},"hd":false,"o":{"a":0,"k":100},"r":1},{"ty":"tr","p":{"a":0,"k":[331.35,377.65]},"a":{"a":0,"k":[32.15,29.85]},"s":{"a":0,"k":[100,100]},"r":{"a":0,"k":0},"o":{"a":0,"k":100},"sk":{"a":0,"k":0},"sa":{"a":0,"k":0}}],"nm":"Object","hd":false},{"ty":"gr","it":[{"d":1,"ty":"rc","s":{"a":0,"k":[2.7,9.5]},"p":{"a":0,"k":[1.35,4.75]},"r":{"a":0,"k":0}},{"ty":"fl","c":{"a":0,"k":[0.149,0.149,0.286,1]},"hd":false,"o":{"a":0,"k":100},"r":1},{"ty":"tr","p":{"a":0,"k":[427.45,402.75]},"a":{"a":0,"k":[1.35,4.75]},"s":{"a":0,"k":[100,100]},"r":{"a":0,"k":0},"o":{"a":0,"k":100},"sk":{"a":0,"k":0},"sa":{"a":0,"k":0}}],"nm":"Object","hd":false},{"ty":"gr","it":[{"d":1,"ty":"rc","s":{"a":0,"k":[64.3,59.7]},"p":{"a":0,"k":[32.15,29.85]},"r":{"a":0,"k":0}},{"ty":"gf","t":1,"s":{"a":0,"k":[25.497,104.281]},"e":{"a":0,"k":[35.429,-7.347]},"g":{"p":8,"k":{"a":0,"k":[0,0.624,0.631,0.878,0.282,0.447,0.353,0.749,0.307,0.42,0.333,0.702,0.399,0.333,0.271,0.549,0.49,0.267,0.22,0.427,0.578,0.216,0.184,0.341,0.663,0.188,0.165,0.29,0.739,0.176,0.157,0.271]}},"hd":false,"o":{"a":0,"k":100},"r":1},{"ty":"tr","p":{"a":0,"k":[395.65,377.65]},"a":{"a":0,"k":[32.15,29.85]},"s":{"a":0,"k":[100,100]},"r":{"a":0,"k":0},"o":{"a":0,"k":100},"sk":{"a":0,"k":0},"sa":{"a":0,"k":0}}],"nm":"Object","hd":false},{"ty":"gr","it":[{"d":1,"ty":"rc","s":{"a":0,"k":[64.3,59.7]},"p":{"a":0,"k":[32.15,29.85]},"r":{"a":0,"k":0}},{"ty":"gf","t":1,"s":{"a":0,"k":[24.958,109.953]},"e":{"a":0,"k":[34.889,-1.674]},"g":{"p":8,"k":{"a":0,"k":[0,0.624,0.631,0.878,0.282,0.447,0.353,0.749,0.307,0.42,0.333,0.702,0.399,0.333,0.271,0.549,0.49,0.267,0.22,0.427,0.578,0.216,0.184,0.341,0.663,0.188,0.165,0.29,0.739,0.176,0.157,0.271]}},"hd":false,"o":{"a":0,"k":100},"r":1},{"ty":"tr","p":{"a":0,"k":[459.95,377.65]},"a":{"a":0,"k":[32.15,29.85]},"s":{"a":0,"k":[100,100]},"r":{"a":0,"k":0},"o":{"a":0,"k":100},"sk":{"a":0,"k":0},"sa":{"a":0,"k":0}}],"nm":"Object","hd":false},{"ty":"gr","it":[{"d":1,"ty":"rc","s":{"a":0,"k":[2.7,52.8]},"p":{"a":0,"k":[1.35,26.4]},"r":{"a":0,"k":0}},{"ty":"fl","c":{"a":0,"k":[0.29,0.282,0.51,1]},"hd":false,"o":{"a":0,"k":100},"r":1},{"ty":"tr","p":{"a":0,"k":[427.45,433.2]},"a":{"a":0,"k":[1.35,26.4]},"s":{"a":0,"k":[100,100]},"r":{"a":0,"k":0},"o":{"a":0,"k":100},"sk":{"a":0,"k":0},"sa":{"a":0,"k":0}}],"nm":"Object","hd":false},{"ty":"gr","it":[{"d":1,"ty":"rc","s":{"a":0,"k":[2.7,52.8]},"p":{"a":0,"k":[1.35,26.4]},"r":{"a":0,"k":0}},{"ty":"fl","c":{"a":0,"k":[0.29,0.282,0.51,1]},"hd":false,"o":{"a":0,"k":100},"r":1},{"ty":"tr","p":{"a":0,"k":[362.15,433.2]},"a":{"a":0,"k":[1.35,26.4]},"s":{"a":0,"k":[100,100]},"r":{"a":0,"k":0},"o":{"a":0,"k":100},"sk":{"a":0,"k":0},"sa":{"a":0,"k":0}}],"nm":"Object","hd":false},{"ty":"gr","it":[{"d":1,"ty":"rc","s":{"a":0,"k":[64.3,52.8]},"p":{"a":0,"k":[32.15,26.4]},"r":{"a":0,"k":0}},{"ty":"gf","t":1,"s":{"a":0,"k":[-4.865,23.328]},"e":{"a":0,"k":[10.919,24.618]},"g":{"p":2,"k":{"a":0,"k":[0,0.929,0.882,1,1,0.788,0.533,0.922,0,1,1,0]}},"hd":false,"o":{"a":0,"k":100},"r":1},{"ty":"tr","p":{"a":0,"k":[331.35,433.2]},"a":{"a":0,"k":[32.15,26.4]},"s":{"a":0,"k":[100,100]},"r":{"a":0,"k":0},"o":{"a":0,"k":100},"sk":{"a":0,"k":0},"sa":{"a":0,"k":0}}],"nm":"Object","hd":false},{"ty":"gr","it":[{"d":1,"ty":"rc","s":{"a":0,"k":[64.3,52.8]},"p":{"a":0,"k":[32.15,26.4]},"r":{"a":0,"k":0}},{"ty":"gf","t":1,"s":{"a":0,"k":[-16.384,-16.585]},"e":{"a":0,"k":[194.567,170.026]},"g":{"p":6,"k":{"a":0,"k":[0,0.894,0.616,0.784,0.155,0.741,0.525,0.773,0.344,0.584,0.431,0.761,0.493,0.482,0.373,0.753,0.584,0.447,0.353,0.749,1,0.624,0.631,0.878]}},"hd":false,"o":{"a":0,"k":100},"r":1},{"ty":"tr","p":{"a":0,"k":[331.35,433.2]},"a":{"a":0,"k":[32.15,26.4]},"s":{"a":0,"k":[100,100]},"r":{"a":0,"k":0},"o":{"a":0,"k":100},"sk":{"a":0,"k":0},"sa":{"a":0,"k":0}}],"nm":"Object","hd":false},{"ty":"gr","it":[{"d":1,"ty":"rc","s":{"a":0,"k":[64.3,52.8]},"p":{"a":0,"k":[32.15,26.4]},"r":{"a":0,"k":0}},{"ty":"gf","t":1,"s":{"a":0,"k":[-11.358,26.713]},"e":{"a":0,"k":[9.27,26.542]},"g":{"p":2,"k":{"a":0,"k":[0,0.929,0.882,1,1,0.788,0.533,0.922,0,1,1,0]}},"hd":false,"o":{"a":0,"k":100},"r":1},{"ty":"tr","p":{"a":0,"k":[395.65,433.2]},"a":{"a":0,"k":[32.15,26.4]},"s":{"a":0,"k":[100,100]},"r":{"a":0,"k":0},"o":{"a":0,"k":100},"sk":{"a":0,"k":0},"sa":{"a":0,"k":0}}],"nm":"Object","hd":false},{"ty":"gr","it":[{"d":1,"ty":"rc","s":{"a":0,"k":[64.3,52.8]},"p":{"a":0,"k":[32.15,26.4]},"r":{"a":0,"k":0}},{"ty":"gf","t":1,"s":{"a":0,"k":[-52.471,-48.478]},"e":{"a":0,"k":[158.48,138.133]},"g":{"p":6,"k":{"a":0,"k":[0,0.894,0.616,0.784,0.155,0.741,0.525,0.773,0.344,0.584,0.431,0.761,0.493,0.482,0.373,0.753,0.584,0.447,0.353,0.749,1,0.624,0.631,0.878]}},"hd":false,"o":{"a":0,"k":100},"r":1},{"ty":"tr","p":{"a":0,"k":[395.65,433.2]},"a":{"a":0,"k":[32.15,26.4]},"s":{"a":0,"k":[100,100]},"r":{"a":0,"k":0},"o":{"a":0,"k":100},"sk":{"a":0,"k":0},"sa":{"a":0,"k":0}}],"nm":"Object","hd":false},{"ty":"gr","it":[{"d":1,"ty":"rc","s":{"a":0,"k":[64.3,52.8]},"p":{"a":0,"k":[32.15,26.4]},"r":{"a":0,"k":0}},{"ty":"gf","t":1,"s":{"a":0,"k":[-12.76,26.353]},"e":{"a":0,"k":[10.537,26.353]},"g":{"p":2,"k":{"a":0,"k":[0,0.929,0.882,1,1,0.788,0.533,0.922,0,1,1,0]}},"hd":false,"o":{"a":0,"k":100},"r":1},{"ty":"tr","p":{"a":0,"k":[459.95,433.2]},"a":{"a":0,"k":[32.15,26.4]},"s":{"a":0,"k":[100,100]},"r":{"a":0,"k":0},"o":{"a":0,"k":100},"sk":{"a":0,"k":0},"sa":{"a":0,"k":0}}],"nm":"Object","hd":false},{"ty":"gr","it":[{"d":1,"ty":"rc","s":{"a":0,"k":[64.3,52.8]},"p":{"a":0,"k":[32.15,26.4]},"r":{"a":0,"k":0}},{"ty":"gf","t":1,"s":{"a":0,"k":[-88.558,-80.37]},"e":{"a":0,"k":[122.392,106.24]},"g":{"p":6,"k":{"a":0,"k":[0,0.894,0.616,0.784,0.155,0.741,0.525,0.773,0.344,0.584,0.431,0.761,0.493,0.482,0.373,0.753,0.584,0.447,0.353,0.749,1,0.624,0.631,0.878]}},"hd":false,"o":{"a":0,"k":100},"r":1},{"ty":"tr","p":{"a":0,"k":[459.95,433.2]},"a":{"a":0,"k":[32.15,26.4]},"s":{"a":0,"k":[100,100]},"r":{"a":0,"k":0},"o":{"a":0,"k":100},"sk":{"a":0,"k":0},"sa":{"a":0,"k":0}}],"nm":"Object","hd":false},{"ty":"tr","p":{"a":0,"k":[395.65,403.7]},"a":{"a":0,"k":[395.65,403.7]},"s":{"a":0,"k":[100,100]},"r":{"a":0,"k":0},"o":{"a":0,"k":100},"sk":{"a":0,"k":0},"sa":{"a":0,"k":0}}],"nm":"Object","hd":false}],"ln":"MID"},{"ind":2,"nm":"BTTM","ks":{"p":{"a":1,"k":[{"t":0,"s":[335.153,430.809,0],"to":[0,0,0],"ti":[0,0,0],"i":{"x":[0.58],"y":[1]},"o":{"x":[0.42],"y":[0]},"e":[335.153,444.557,0]},{"t":25,"s":[335.153,444.557,0],"to":[0,0,0],"ti":[0,0,0],"i":{"x":[0.58],"y":[1]},"o":{"x":[0.42],"y":[0]},"e":[335.153,430.809,0]},{"t":50,"s":[335.153,430.809,0],"to":[0,0,0],"ti":[0,0,0],"i":{"x":[0.58],"y":[1]},"o":{"x":[0.42],"y":[0]},"e":[335.153,444.557,0]},{"t":75,"s":[335.153,444.557,0],"to":[0,0,0],"ti":[0,0,0],"i":{"x":[0.58],"y":[1]},"o":{"x":[0.42],"y":[0]},"e":[335.153,430.809,0]},{"t":100,"s":[335.153,430.809,0]}]},"a":{"a":0,"k":[395.6,460.5,0]},"s":{"a":0,"k":[100,100,100]},"r":{"a":0,"k":0},"o":{"a":0,"k":100}},"ao":0,"ip":0,"op":100,"st":0,"bm":0,"sr":1,"ty":4,"shapes":[{"ty":"gr","it":[{"ty":"gr","it":[{"ty":"sh","d":1,"ks":{"a":0,"k":{"i":[[0,0],[0,0],[0,0],[0,0],[0,0]],"o":[[0,0],[0,0],[0,0],[0,0],[0,0]],"v":[[448.9,465.7],[448.9,465.7],[448.9,465.7],[448.9,465.7],[448.9,465.7]],"c":true},"hd":false}},{"ty":"sh","d":1,"ks":{"a":0,"k":{"i":[[0,0],[0.5,0.2],[0,0],[0.5,0.1],[0,0],[0,0],[0,0],[0,0],[0,0],[0.3,0.1],[0.5,0.2],[0,0],[0,0],[0,0],[0,0],[0,0],[0,0],[0,0],[0,0],[0,0],[0,0],[0,0],[0,0],[0,0],[0,0],[0,0],[0,0],[0,0],[0,0],[0,0],[0,0],[0,0],[0,0],[0,0],[0,0],[0,0],[0,0],[0,0],[0,0],[0,0],[0,0],[0,0],[0,0],[0,0],[0,0],[0,0],[0,0],[0,0],[0,0],[0,0],[0,0],[0,0],[0,0],[0,0],[0,0],[0,0],[0,0],[0,0],[0,0]],"o":[[-0.5,-0.2],[0,0],[-0.5,-0.2],[0,0],[0,0],[0,0],[0,0],[0,0],[-0.2,-0.1],[-0.5,-0.2],[0,0],[0,0],[0,0],[0,0],[0,0],[0,0],[0,0],[0,0],[0,0],[0,0],[0,0],[0,0],[0,0],[0,0],[0,0],[0,0],[0,0],[0,0],[0,0],[0,0],[0,0],[0,0],[0,0],[0,0],[0,0],[0,0],[0,0],[0,0],[0,0],[0,0],[0,0],[0,0],[0,0],[0,0],[0,0],[0,0],[0,0],[0,0],[0,0],[0,0],[0,0],[0,0],[0,0],[0,0],[0,0],[0,0],[0,0],[0,0],[0,0]],"v":[[501.5,414.6],[500,414.1],[500,414.1],[498.4,413.6],[498.4,413.6],[447.7,430.5],[398.9,414.2],[448.7,397.6],[448.5,397.1],[447.8,396.9],[446.2,396.4],[446.2,396.4],[395.7,413],[345.3,396.1],[343.4,396.7],[342.1,397.1],[392.5,414],[343.6,430.3],[293.2,413.4],[291.3,414.1],[290.2,414.5],[290.2,414.5],[290.2,414.6],[340.6,431.5],[289.9,448.4],[290.2,448.5],[290.2,448.5],[291.3,448.9],[291.3,448.9],[291.4,448.9],[291.5,448.9],[293,449.4],[293,449.4],[343.6,432.5],[392.3,448.9],[342.2,465.6],[342.3,465.8],[343.4,466.2],[344.2,466.5],[344.4,466.6],[345.1,466.8],[395.4,450],[445.6,466.9],[446.6,466.6],[446.7,466.6],[447.7,466.3],[448.8,465.9],[398.6,449.1],[447.6,432.8],[498,449.7],[499.6,449.2],[500,449.1],[500,449.1],[501.1,448.7],[501.1,448.7],[501.1,448.7],[501.1,448.7],[450.8,431.8],[501.5,414.6]],"c":true},"hd":false}},{"ty":"sh","d":1,"ks":{"a":0,"k":{"i":[[0,0],[0,0],[0,0],[0,0],[0,0]],"o":[[0,0],[0,0],[0,0],[0,0],[0,0]],"v":[[346.8,431.4],[395.7,415.1],[444.5,431.4],[395.5,447.7],[346.8,431.4]],"c":true},"hd":false}},{"ty":"gf","t":1,"s":{"a":0,"k":[515.04,429.307]},"e":{"a":0,"k":[312.599,432.871]},"g":{"p":5,"k":{"a":0,"k":[0,0.267,0.267,0.478,0.215,0.282,0.275,0.502,0.49,0.322,0.294,0.561,0.796,0.392,0.325,0.663,1,0.447,0.353,0.749]}},"hd":false,"o":{"a":0,"k":100},"r":1},{"ty":"tr","p":{"a":0,"k":[395.7,431.5]},"a":{"a":0,"k":[395.7,431.5]},"s":{"a":0,"k":[100,100]},"r":{"a":0,"k":0},"o":{"a":0,"k":100},"sk":{"a":0,"k":0},"sa":{"a":0,"k":0}}],"nm":"Object","hd":false},{"ty":"gr","it":[{"ty":"sh","d":1,"ks":{"a":0,"k":{"i":[[0,0],[0,0],[0,0],[0,0],[0,0],[0,0],[0,0],[0,0]],"o":[[0,0],[0,0],[0,0],[0,0],[0,0],[0,0],[0,0],[0,0]],"v":[[292.3,449.1],[292.3,507.3],[290.2,506.7],[290.2,448.3],[291.2,448.7],[291.3,448.7],[291.4,448.8],[291.5,448.8]],"c":true},"hd":false}},{"ty":"fl","c":{"a":0,"k":[0.502,0.322,0.6,1]},"hd":false,"o":{"a":0,"k":100},"r":1},{"ty":"tr","p":{"a":0,"k":[291.25,477.8]},"a":{"a":0,"k":[291.25,477.8]},"s":{"a":0,"k":[100,100]},"r":{"a":0,"k":0},"o":{"a":0,"k":100},"sk":{"a":0,"k":0},"sa":{"a":0,"k":0}}],"nm":"Object","hd":false},{"ty":"gr","it":[{"ty":"sh","d":1,"ks":{"a":0,"k":{"i":[[0,0],[0,0],[0,0],[0,0],[0,0],[0,0],[0,0],[0,0],[0,0],[0,0],[-17.4,-5.8]],"o":[[0,0],[0,0],[0,0],[0,0],[0,0],[0,0],[0,0],[0,0],[0,0],[17.3,5.7],[0,0]],"v":[[395.6,448.7],[343.5,466],[342.4,465.6],[342.4,465.6],[293,449.3],[293,449.3],[291.5,448.8],[291.4,448.8],[291.3,448.8],[343.5,431.5],[395.6,448.7]],"c":true},"hd":false}},{"ty":"gf","t":1,"s":{"a":0,"k":[276.28,456.069]},"e":{"a":0,"k":[349.824,448.007]},"g":{"p":2,"k":{"a":0,"k":[0,0.98,0.863,1,1,0.788,0.533,0.922,0,1,1,0]}},"hd":false,"o":{"a":0,"k":100},"r":1},{"ty":"tr","p":{"a":0,"k":[343.45,448.75]},"a":{"a":0,"k":[343.45,448.75]},"s":{"a":0,"k":[100,100]},"r":{"a":0,"k":0},"o":{"a":0,"k":100},"sk":{"a":0,"k":0},"sa":{"a":0,"k":0}}],"nm":"Object","hd":false},{"ty":"gr","it":[{"ty":"sh","d":1,"ks":{"a":0,"k":{"i":[[0,0],[0,0],[0,0],[0,0],[0,0],[0,0],[0,0],[0,0],[0,0],[0,0],[-17.4,-5.8]],"o":[[0,0],[0,0],[0,0],[0,0],[0,0],[0,0],[0,0],[0,0],[0,0],[17.3,5.7],[0,0]],"v":[[395.6,448.7],[343.5,466],[342.4,465.6],[342.4,465.6],[293,449.3],[293,449.3],[291.5,448.8],[291.4,448.8],[291.3,448.8],[343.5,431.5],[395.6,448.7]],"c":true},"hd":false}},{"ty":"gf","t":1,"s":{"a":0,"k":[287.874,478.299]},"e":{"a":0,"k":[485.378,373.097]},"g":{"p":3,"k":{"a":0,"k":[0,0.694,0.553,0.839,0.512,0.259,0.357,0.698,1,0.341,0.282,0.686]}},"hd":false,"o":{"a":0,"k":100},"r":1},{"ty":"tr","p":{"a":0,"k":[343.45,448.75]},"a":{"a":0,"k":[343.45,448.75]},"s":{"a":0,"k":[100,100]},"r":{"a":0,"k":0},"o":{"a":0,"k":100},"sk":{"a":0,"k":0},"sa":{"a":0,"k":0}}],"nm":"Object","hd":false},{"ty":"gr","it":[{"ty":"sh","d":1,"ks":{"a":0,"k":{"i":[[0,0],[0,0],[0,0],[0,0],[0,0],[0,0],[0,0],[0,0],[0,0],[0,0],[0,0],[0,0],[-17.4,-5.7]],"o":[[0,0],[0,0],[0,0],[0,0],[0,0],[0,0],[0,0],[0,0],[0,0],[0,0],[0,0],[17.5,5.9],[0,0]],"v":[[447.8,466],[446.8,466.3],[446.7,466.3],[445.7,466.6],[395.6,483.3],[395.6,483.3],[345.1,466.5],[344.4,466.3],[344.2,466.2],[343.4,465.9],[395.5,448.6],[395.5,448.6],[447.8,466]],"c":true},"hd":false}},{"ty":"gf","t":1,"s":{"a":0,"k":[360.405,510.496]},"e":{"a":0,"k":[396.167,465.323]},"g":{"p":2,"k":{"a":0,"k":[0,0.98,0.863,1,1,0.788,0.533,0.922,0,1,1,0]}},"hd":false,"o":{"a":0,"k":100},"r":1},{"ty":"tr","p":{"a":0,"k":[395.6,465.95]},"a":{"a":0,"k":[395.6,465.95]},"s":{"a":0,"k":[100,100]},"r":{"a":0,"k":0},"o":{"a":0,"k":100},"sk":{"a":0,"k":0},"sa":{"a":0,"k":0}}],"nm":"Object","hd":false},{"ty":"gr","it":[{"ty":"sh","d":1,"ks":{"a":0,"k":{"i":[[0,0],[0,0],[0,0],[0,0],[0,0],[0,0],[0,0],[0,0],[0,0],[0,0],[0,0],[0,0],[-17.4,-5.7]],"o":[[0,0],[0,0],[0,0],[0,0],[0,0],[0,0],[0,0],[0,0],[0,0],[0,0],[0,0],[17.5,5.9],[0,0]],"v":[[447.8,466],[446.8,466.3],[446.7,466.3],[445.7,466.6],[395.6,483.3],[395.6,483.3],[345.1,466.5],[344.4,466.3],[344.2,466.2],[343.4,465.9],[395.5,448.6],[395.5,448.6],[447.8,466]],"c":true},"hd":false}},{"ty":"gf","t":1,"s":{"a":0,"k":[306.595,513.445]},"e":{"a":0,"k":[504.098,408.242]},"g":{"p":3,"k":{"a":0,"k":[0,0.694,0.553,0.839,0.512,0.259,0.357,0.698,1,0.341,0.282,0.686]}},"hd":false,"o":{"a":0,"k":100},"r":1},{"ty":"tr","p":{"a":0,"k":[395.6,465.95]},"a":{"a":0,"k":[395.6,465.95]},"s":{"a":0,"k":[100,100]},"r":{"a":0,"k":0},"o":{"a":0,"k":100},"sk":{"a":0,"k":0},"sa":{"a":0,"k":0}}],"nm":"Object","hd":false},{"ty":"gr","it":[{"ty":"sh","d":1,"ks":{"a":0,"k":{"i":[[0,0],[0,0],[0,0],[0,0],[0,0],[0,0],[0,0],[0,0]],"o":[[0,0],[0,0],[0,0],[0,0],[0,0],[0,0],[0,0],[0,0]],"v":[[344.5,466.4],[344.5,524.7],[343.4,524.3],[343.2,524.2],[342.4,524],[342.4,465.6],[343.5,466],[344.3,466.3]],"c":true},"hd":false}},{"ty":"fl","c":{"a":0,"k":[0.502,0.322,0.6,1]},"hd":false,"o":{"a":0,"k":100},"r":1},{"ty":"tr","p":{"a":0,"k":[343.45,495.15]},"a":{"a":0,"k":[343.45,495.15]},"s":{"a":0,"k":[100,100]},"r":{"a":0,"k":0},"o":{"a":0,"k":100},"sk":{"a":0,"k":0},"sa":{"a":0,"k":0}}],"nm":"Object","hd":false},{"ty":"gr","it":[{"ty":"sh","d":1,"ks":{"a":0,"k":{"i":[[0,0],[0,0],[0,0],[0,0],[0,0],[0,0],[0,0]],"o":[[0,0],[0,0],[0,0],[0,0],[0,0],[0,0],[0,0]],"v":[[501.1,448.3],[501.1,506.7],[498.9,507.3],[498.9,449.1],[499.6,448.9],[500,448.7],[500,448.7]],"c":true},"hd":false}},{"ty":"fl","c":{"a":0,"k":[0.176,0.141,0.31,1]},"hd":false,"o":{"a":0,"k":100},"r":1},{"ty":"tr","p":{"a":0,"k":[500,477.8]},"a":{"a":0,"k":[500,477.8]},"s":{"a":0,"k":[100,100]},"r":{"a":0,"k":0},"o":{"a":0,"k":100},"sk":{"a":0,"k":0},"sa":{"a":0,"k":0}}],"nm":"Object","hd":false},{"ty":"gr","it":[{"ty":"sh","d":1,"ks":{"a":0,"k":{"i":[[0,0],[0,0],[0,0],[0,0],[0,0],[0,0],[0,0],[0,0],[17.4,5.8],[0,0],[0,0],[-17.4,-5.8]],"o":[[0,0],[0,0],[0,0],[0,0],[0,0],[0,0],[0,0],[-17.4,-5.8],[0,0],[0,0],[17.4,5.8],[0,0]],"v":[[500,448.7],[499.6,448.8],[498,449.3],[448.9,465.6],[448.9,465.6],[448.9,465.6],[448.9,465.6],[447.8,466],[395.6,448.7],[447.8,431.4],[447.8,431.4],[500,448.7]],"c":true},"hd":false}},{"ty":"gf","t":1,"s":{"a":0,"k":[310.941,521.604]},"e":{"a":0,"k":[508.444,416.401]},"g":{"p":3,"k":{"a":0,"k":[0,0.694,0.553,0.839,0.512,0.259,0.357,0.698,1,0.341,0.282,0.686]}},"hd":false,"o":{"a":0,"k":100},"r":1},{"ty":"tr","p":{"a":0,"k":[447.8,448.7]},"a":{"a":0,"k":[447.8,448.7]},"s":{"a":0,"k":[100,100]},"r":{"a":0,"k":0},"o":{"a":0,"k":100},"sk":{"a":0,"k":0},"sa":{"a":0,"k":0}}],"nm":"Object","hd":false},{"ty":"gr","it":[{"ty":"sh","d":1,"ks":{"a":0,"k":{"i":[[0,0],[0,0],[0,0],[17.4,5.8],[0,0],[-17.4,-5.8]],"o":[[0,0],[0,0],[-17.4,-5.8],[0,0],[17.4,5.7],[0,0]],"v":[[447.8,431.4],[395.6,448.7],[395.6,448.7],[343.4,431.4],[395.6,414.1],[447.8,431.4]],"c":true},"hd":false}},{"ty":"gf","t":1,"s":{"a":0,"k":[321.88,443.539]},"e":{"a":0,"k":[404.589,429.901]},"g":{"p":2,"k":{"a":0,"k":[0,0.98,0.863,1,1,0.788,0.533,0.922,0,1,1,0]}},"hd":false,"o":{"a":0,"k":100},"r":1},{"ty":"tr","p":{"a":0,"k":[395.6,431.4]},"a":{"a":0,"k":[395.6,431.4]},"s":{"a":0,"k":[100,100]},"r":{"a":0,"k":0},"o":{"a":0,"k":100},"sk":{"a":0,"k":0},"sa":{"a":0,"k":0}}],"nm":"Object","hd":false},{"ty":"gr","it":[{"ty":"sh","d":1,"ks":{"a":0,"k":{"i":[[0,0],[0,0],[0,0],[17.4,5.8],[0,0],[-17.4,-5.8]],"o":[[0,0],[0,0],[-17.4,-5.8],[0,0],[17.4,5.7],[0,0]],"v":[[447.8,431.4],[395.6,448.7],[395.6,448.7],[343.4,431.4],[395.6,414.1],[447.8,431.4]],"c":true},"hd":false}},{"ty":"gf","t":1,"s":{"a":0,"k":[292.219,486.457]},"e":{"a":0,"k":[489.723,381.254]},"g":{"p":3,"k":{"a":0,"k":[0,0.694,0.553,0.839,0.512,0.259,0.357,0.698,1,0.341,0.282,0.686]}},"hd":false,"o":{"a":0,"k":100},"r":1},{"ty":"tr","p":{"a":0,"k":[395.6,431.4]},"a":{"a":0,"k":[395.6,431.4]},"s":{"a":0,"k":[100,100]},"r":{"a":0,"k":0},"o":{"a":0,"k":100},"sk":{"a":0,"k":0},"sa":{"a":0,"k":0}}],"nm":"Object","hd":false},{"ty":"gr","it":[{"ty":"sh","d":1,"ks":{"a":0,"k":{"i":[[0,0],[0,0],[0,0],[0,0],[0,0],[0,0],[0,0],[0,0],[0,0],[0,0]],"o":[[0,0],[0,0],[0,0],[0,0],[0,0],[0,0],[0,0],[0,0],[0,0],[0,0]],"v":[[448.9,465.6],[448.9,524],[448.2,524.2],[448.2,524.2],[448,524.3],[447.8,524.3],[446.7,524.7],[446.7,466.4],[446.8,466.4],[447.8,466]],"c":true},"hd":false}},{"ty":"fl","c":{"a":0,"k":[0.176,0.141,0.31,1]},"hd":false,"o":{"a":0,"k":100},"r":1},{"ty":"tr","p":{"a":0,"k":[447.8,495.15]},"a":{"a":0,"k":[447.8,495.15]},"s":{"a":0,"k":[100,100]},"r":{"a":0,"k":0},"o":{"a":0,"k":100},"sk":{"a":0,"k":0},"sa":{"a":0,"k":0}}],"nm":"Object","hd":false},{"ty":"gr","it":[{"ty":"sh","d":1,"ks":{"a":0,"k":{"i":[[0,0],[0,0],[0,0],[0,0],[0,0],[0,0],[17.4,5.7],[0,0],[0,0],[-0.5,-0.2],[0,0],[0,0]],"o":[[0,0],[0,0],[0,0],[0,0],[0,0],[-17.4,-5.8],[0,0],[0,0],[0.5,0.2],[0,0],[0,0],[0,0]],"v":[[552.2,431.4],[501.1,448.4],[501.1,448.4],[501.1,448.4],[500,448.8],[500,448.8],[447.8,431.5],[500,414],[500,414],[501.5,414.5],[501.5,414.5],[552.2,431.4]],"c":true},"hd":false}},{"ty":"gf","t":1,"s":{"a":0,"k":[315.289,529.768]},"e":{"a":0,"k":[512.793,424.565]},"g":{"p":3,"k":{"a":0,"k":[0,0.694,0.553,0.839,0.512,0.259,0.357,0.698,1,0.341,0.282,0.686]}},"hd":false,"o":{"a":0,"k":100},"r":1},{"ty":"tr","p":{"a":0,"k":[500,431.4]},"a":{"a":0,"k":[500,431.4]},"s":{"a":0,"k":[100,100]},"r":{"a":0,"k":0},"o":{"a":0,"k":100},"sk":{"a":0,"k":0},"sa":{"a":0,"k":0}}],"nm":"Object","hd":false},{"ty":"gr","it":[{"ty":"sh","d":1,"ks":{"a":0,"k":{"i":[[0,0],[0,0],[0,0],[17.4,5.8],[0,0],[-0.3,0],[-16.7,-5.6],[0,0],[-0.5,-0.1]],"o":[[0,0],[0,0],[-17.4,-5.8],[0,0],[0.2,0.1],[16.6,5.5],[0,0],[0.5,0.2],[0,0]],"v":[[500,414],[447.8,431.3],[447.8,431.3],[395.6,414],[447.8,396.7],[448.5,396.9],[498.4,413.5],[498.4,413.5],[500,414]],"c":true},"hd":false}},{"ty":"gf","t":1,"s":{"a":0,"k":[296.563,494.611]},"e":{"a":0,"k":[494.066,389.408]},"g":{"p":3,"k":{"a":0,"k":[0,0.694,0.553,0.839,0.512,0.259,0.357,0.698,1,0.341,0.282,0.686]}},"hd":false,"o":{"a":0,"k":100},"r":1},{"ty":"tr","p":{"a":0,"k":[447.8,414]},"a":{"a":0,"k":[447.8,414]},"s":{"a":0,"k":[100,100]},"r":{"a":0,"k":0},"o":{"a":0,"k":100},"sk":{"a":0,"k":0},"sa":{"a":0,"k":0}}],"nm":"Object","hd":false},{"ty":"gr","it":[{"ty":"sh","d":1,"ks":{"a":0,"k":{"i":[[0,0],[0,0],[17.4,5.7],[0,0],[0,0],[-16.9,-5.6],[0,0],[-0.5,-0.2]],"o":[[0,0],[-17.4,-5.8],[0,0],[0,0],[16.9,5.6],[0,0],[0.6,0.2],[0,0]],"v":[[447.8,396.7],[395.6,414],[343.4,396.7],[345.3,396.1],[395.6,379.4],[446.2,396.2],[446.2,396.2],[447.8,396.7]],"c":true},"hd":false}},{"ty":"gf","t":1,"s":{"a":0,"k":[331.59,406.577]},"e":{"a":0,"k":[394.108,396.959]},"g":{"p":2,"k":{"a":0,"k":[0,0.98,0.863,1,1,0.788,0.533,0.922,0,1,1,0]}},"hd":false,"o":{"a":0,"k":100},"r":1},{"ty":"tr","p":{"a":0,"k":[395.6,396.7]},"a":{"a":0,"k":[395.6,396.7]},"s":{"a":0,"k":[100,100]},"r":{"a":0,"k":0},"o":{"a":0,"k":100},"sk":{"a":0,"k":0},"sa":{"a":0,"k":0}}],"nm":"Object","hd":false},{"ty":"gr","it":[{"ty":"sh","d":1,"ks":{"a":0,"k":{"i":[[0,0],[0,0],[17.4,5.7],[0,0],[0,0],[-16.9,-5.6],[0,0],[-0.5,-0.2]],"o":[[0,0],[-17.4,-5.8],[0,0],[0,0],[16.9,5.6],[0,0],[0.6,0.2],[0,0]],"v":[[447.8,396.7],[395.6,414],[343.4,396.7],[345.3,396.1],[395.6,379.4],[446.2,396.2],[446.2,396.2],[447.8,396.7]],"c":true},"hd":false}},{"ty":"gf","t":1,"s":{"a":0,"k":[277.84,459.462]},"e":{"a":0,"k":[475.343,354.259]},"g":{"p":3,"k":{"a":0,"k":[0,0.694,0.553,0.839,0.512,0.259,0.357,0.698,1,0.341,0.282,0.686]}},"hd":false,"o":{"a":0,"k":100},"r":1},{"ty":"tr","p":{"a":0,"k":[395.6,396.7]},"a":{"a":0,"k":[395.6,396.7]},"s":{"a":0,"k":[100,100]},"r":{"a":0,"k":0},"o":{"a":0,"k":100},"sk":{"a":0,"k":0},"sa":{"a":0,"k":0}}],"nm":"Object","hd":false},{"ty":"gr","it":[{"ty":"sh","d":1,"ks":{"a":0,"k":{"i":[[0,0],[0,0],[0,0],[0,0],[0,0],[0,0],[0,0],[0,0],[0,0],[0,0],[-17.4,-5.8]],"o":[[0,0],[0,0],[0,0],[0,0],[0,0],[0,0],[0,0],[0,0],[0,0],[17.4,5.9],[0,0]],"v":[[343.4,431.4],[291.2,448.7],[291.2,448.7],[290.1,448.3],[290.1,448.3],[289.8,448.2],[239,431.3],[290.1,414.3],[290.1,414.3],[291.2,413.9],[343.4,431.4]],"c":true},"hd":false}},{"ty":"gf","t":1,"s":{"a":0,"k":[246.483,446.005]},"e":{"a":0,"k":[273.417,437.21]},"g":{"p":2,"k":{"a":0,"k":[0,0.98,0.863,1,1,0.788,0.533,0.922,0,1,1,0]}},"hd":false,"o":{"a":0,"k":100},"r":1},{"ty":"tr","p":{"a":0,"k":[291.2,431.3]},"a":{"a":0,"k":[291.2,431.3]},"s":{"a":0,"k":[100,100]},"r":{"a":0,"k":0},"o":{"a":0,"k":100},"sk":{"a":0,"k":0},"sa":{"a":0,"k":0}}],"nm":"Object","hd":false},{"ty":"gr","it":[{"ty":"sh","d":1,"ks":{"a":0,"k":{"i":[[0,0],[0,0],[0,0],[0,0],[0,0],[0,0],[0,0],[0,0],[0,0],[0,0],[-17.4,-5.8]],"o":[[0,0],[0,0],[0,0],[0,0],[0,0],[0,0],[0,0],[0,0],[0,0],[17.4,5.9],[0,0]],"v":[[343.4,431.4],[291.2,448.7],[291.2,448.7],[290.1,448.3],[290.1,448.3],[289.8,448.2],[239,431.3],[290.1,414.3],[290.1,414.3],[291.2,413.9],[343.4,431.4]],"c":true},"hd":false}},{"ty":"gf","t":1,"s":{"a":0,"k":[269.154,443.155]},"e":{"a":0,"k":[466.657,337.952]},"g":{"p":3,"k":{"a":0,"k":[0,0.694,0.553,0.839,0.512,0.259,0.357,0.698,1,0.341,0.282,0.686]}},"hd":false,"o":{"a":0,"k":100},"r":1},{"ty":"tr","p":{"a":0,"k":[291.2,431.3]},"a":{"a":0,"k":[291.2,431.3]},"s":{"a":0,"k":[100,100]},"r":{"a":0,"k":0},"o":{"a":0,"k":100},"sk":{"a":0,"k":0},"sa":{"a":0,"k":0}}],"nm":"Object","hd":false},{"ty":"gr","it":[{"ty":"sh","d":1,"ks":{"a":0,"k":{"i":[[0,0],[0,0],[17.4,5.8],[0,0],[0,0],[0,0],[-17.4,-5.8]],"o":[[0,0],[-17.4,-5.8],[0,0],[0,0],[0,0],[17.5,5.7],[0,0]],"v":[[395.6,414.1],[343.4,431.4],[291.2,414.1],[293.1,413.4],[342,397.2],[343.3,396.8],[395.6,414.1]],"c":true},"hd":false}},{"ty":"gf","t":1,"s":{"a":0,"k":[280.614,416.733]},"e":{"a":0,"k":[351.594,413.709]},"g":{"p":2,"k":{"a":0,"k":[0,0.98,0.863,1,1,0.788,0.533,0.922,0,1,1,0]}},"hd":false,"o":{"a":0,"k":100},"r":1},{"ty":"tr","p":{"a":0,"k":[343.4,414.1]},"a":{"a":0,"k":[343.4,414.1]},"s":{"a":0,"k":[100,100]},"r":{"a":0,"k":0},"o":{"a":0,"k":100},"sk":{"a":0,"k":0},"sa":{"a":0,"k":0}}],"nm":"Object","hd":false},{"ty":"gr","it":[{"ty":"sh","d":1,"ks":{"a":0,"k":{"i":[[0,0],[0,0],[17.4,5.8],[0,0],[0,0],[0,0],[-17.4,-5.8]],"o":[[0,0],[-17.4,-5.8],[0,0],[0,0],[0,0],[17.5,5.7],[0,0]],"v":[[395.6,414.1],[343.4,431.4],[291.2,414.1],[293.1,413.4],[342,397.2],[343.3,396.8],[395.6,414.1]],"c":true},"hd":false}},{"ty":"gf","t":1,"s":{"a":0,"k":[273.498,451.31]},"e":{"a":0,"k":[471.001,346.108]},"g":{"p":3,"k":{"a":0,"k":[0,0.694,0.553,0.839,0.512,0.259,0.357,0.698,1,0.341,0.282,0.686]}},"hd":false,"o":{"a":0,"k":100},"r":1},{"ty":"tr","p":{"a":0,"k":[343.4,414.1]},"a":{"a":0,"k":[343.4,414.1]},"s":{"a":0,"k":[100,100]},"r":{"a":0,"k":0},"o":{"a":0,"k":100},"sk":{"a":0,"k":0},"sa":{"a":0,"k":0}}],"nm":"Object","hd":false},{"ty":"gr","it":[{"ty":"sh","d":1,"ks":{"a":0,"k":{"i":[[0,0],[0,0],[0,0],[0,0],[0,0],[0,0],[0,0],[0,0]],"o":[[0,0],[0,0],[0,0],[0,0],[0,0],[0,0],[0,0],[0,0]],"v":[[291.3,448.7],[291.3,507],[290.2,506.6],[257,495.6],[239.1,489.6],[239.1,431.4],[290.2,448.4],[291.2,448.7]],"c":true},"hd":false}},{"ty":"gf","t":1,"s":{"a":0,"k":[231.389,464.189]},"e":{"a":0,"k":[258.27,468.171]},"g":{"p":2,"k":{"a":0,"k":[0,0.98,0.863,1,1,0.788,0.533,0.922,0,1,1,0]}},"hd":false,"o":{"a":0,"k":100},"r":1},{"ty":"tr","p":{"a":0,"k":[265.2,469.2]},"a":{"a":0,"k":[265.2,469.2]},"s":{"a":0,"k":[100,100]},"r":{"a":0,"k":0},"o":{"a":0,"k":100},"sk":{"a":0,"k":0},"sa":{"a":0,"k":0}}],"nm":"Object","hd":false},{"ty":"gr","it":[{"ty":"sh","d":1,"ks":{"a":0,"k":{"i":[[0,0],[0,0],[0,0],[0,0],[0,0],[0,0],[0,0],[0,0]],"o":[[0,0],[0,0],[0,0],[0,0],[0,0],[0,0],[0,0],[0,0]],"v":[[291.3,448.7],[291.3,507],[290.2,506.6],[257,495.6],[239.1,489.6],[239.1,431.4],[290.2,448.4],[291.2,448.7]],"c":true},"hd":false}},{"ty":"gf","t":1,"s":{"a":0,"k":[241.06,443.434]},"e":{"a":0,"k":[619.633,847.949]},"g":{"p":5,"k":{"a":0,"k":[0,0.918,0.471,0.78,0.196,0.702,0.408,0.761,0.368,0.541,0.365,0.749,0.502,0.439,0.337,0.741,0.584,0.404,0.325,0.737]}},"hd":false,"o":{"a":0,"k":100},"r":1},{"ty":"tr","p":{"a":0,"k":[265.2,469.2]},"a":{"a":0,"k":[265.2,469.2]},"s":{"a":0,"k":[100,100]},"r":{"a":0,"k":0},"o":{"a":0,"k":100},"sk":{"a":0,"k":0},"sa":{"a":0,"k":0}}],"nm":"Object","hd":false},{"ty":"gr","it":[{"ty":"sh","d":1,"ks":{"a":0,"k":{"i":[[0,0],[0,0],[0,0],[0,0],[0,0],[0,0],[0,0]],"o":[[0,0],[0,0],[0,0],[0,0],[0,0],[0,0],[0,0]],"v":[[395.6,483.4],[395.6,541.6],[344.5,524.7],[343.4,524.3],[343.4,466],[344.3,466.3],[344.5,466.4]],"c":true},"hd":false}},{"ty":"gf","t":1,"s":{"a":0,"k":[337.73,505.368]},"e":{"a":0,"k":[365.622,504.029]},"g":{"p":2,"k":{"a":0,"k":[0,0.98,0.863,1,1,0.788,0.533,0.922,0,1,1,0]}},"hd":false,"o":{"a":0,"k":100},"r":1},{"ty":"tr","p":{"a":0,"k":[369.5,503.8]},"a":{"a":0,"k":[369.5,503.8]},"s":{"a":0,"k":[100,100]},"r":{"a":0,"k":0},"o":{"a":0,"k":100},"sk":{"a":0,"k":0},"sa":{"a":0,"k":0}}],"nm":"Object","hd":false},{"ty":"gr","it":[{"ty":"sh","d":1,"ks":{"a":0,"k":{"i":[[0,0],[0,0],[0,0],[0,0],[0,0],[0,0],[0,0]],"o":[[0,0],[0,0],[0,0],[0,0],[0,0],[0,0],[0,0]],"v":[[395.6,483.4],[395.6,541.6],[344.5,524.7],[343.4,524.3],[343.4,466],[344.3,466.3],[344.5,466.4]],"c":true},"hd":false}},{"ty":"gf","t":1,"s":{"a":0,"k":[279.405,407.538]},"e":{"a":0,"k":[657.978,812.055]},"g":{"p":5,"k":{"a":0,"k":[0,0.918,0.471,0.78,0.196,0.702,0.408,0.761,0.368,0.541,0.365,0.749,0.502,0.439,0.337,0.741,0.584,0.404,0.325,0.737]}},"hd":false,"o":{"a":0,"k":100},"r":1},{"ty":"tr","p":{"a":0,"k":[369.5,503.8]},"a":{"a":0,"k":[369.5,503.8]},"s":{"a":0,"k":[100,100]},"r":{"a":0,"k":0},"o":{"a":0,"k":100},"sk":{"a":0,"k":0},"sa":{"a":0,"k":0}}],"nm":"Object","hd":false},{"ty":"gr","it":[{"ty":"sh","d":1,"ks":{"a":0,"k":{"i":[[0,0],[0,0],[0,0],[0,0],[0,0],[0,0],[0,0],[0,0],[0,0],[0,0]],"o":[[0,0],[0,0],[0,0],[0,0],[0,0],[0,0],[0,0],[0,0],[0,0],[0,0]],"v":[[343.4,466],[343.4,524.3],[343.2,524.2],[342.4,524],[292.3,507.3],[291.3,507],[291.3,448.7],[291.4,448.8],[291.5,448.8],[342.4,465.7]],"c":true},"hd":false}},{"ty":"gf","t":1,"s":{"a":0,"k":[282.009,483.434]},"e":{"a":0,"k":[307.583,485.669]},"g":{"p":2,"k":{"a":0,"k":[0,0.98,0.863,1,1,0.788,0.533,0.922,0,1,1,0]}},"hd":false,"o":{"a":0,"k":100},"r":1},{"ty":"tr","p":{"a":0,"k":[317.35,486.5]},"a":{"a":0,"k":[317.35,486.5]},"s":{"a":0,"k":[100,100]},"r":{"a":0,"k":0},"o":{"a":0,"k":100},"sk":{"a":0,"k":0},"sa":{"a":0,"k":0}}],"nm":"Object","hd":false},{"ty":"gr","it":[{"ty":"sh","d":1,"ks":{"a":0,"k":{"i":[[0,0],[0,0],[0,0],[0,0],[0,0],[0,0],[0,0],[0,0],[0,0],[0,0]],"o":[[0,0],[0,0],[0,0],[0,0],[0,0],[0,0],[0,0],[0,0],[0,0],[0,0]],"v":[[343.4,466],[343.4,524.3],[343.2,524.2],[342.4,524],[292.3,507.3],[291.3,507],[291.3,448.7],[291.4,448.8],[291.5,448.8],[342.4,465.7]],"c":true},"hd":false}},{"ty":"gf","t":1,"s":{"a":0,"k":[260.236,425.492]},"e":{"a":0,"k":[638.781,829.977]},"g":{"p":5,"k":{"a":0,"k":[0,0.918,0.471,0.78,0.196,0.702,0.408,0.761,0.368,0.541,0.365,0.749,0.502,0.439,0.337,0.741,0.584,0.404,0.325,0.737]}},"hd":false,"o":{"a":0,"k":100},"r":1},{"ty":"tr","p":{"a":0,"k":[317.35,486.5]},"a":{"a":0,"k":[317.35,486.5]},"s":{"a":0,"k":[100,100]},"r":{"a":0,"k":0},"o":{"a":0,"k":100},"sk":{"a":0,"k":0},"sa":{"a":0,"k":0}}],"nm":"Object","hd":false},{"ty":"gr","it":[{"ty":"sh","d":1,"ks":{"a":0,"k":{"i":[[0,0],[0,0],[0,0],[0,0],[0,0],[0,0]],"o":[[0,0],[0,0],[0,0],[0,0],[0,0],[0,0]],"v":[[552.2,431.4],[552.2,489.6],[501.1,506.6],[500,507],[500,448.7],[501.1,448.4]],"c":true},"hd":false}},{"ty":"gf","t":1,"s":{"a":0,"k":[499.992,469.191]},"e":{"a":0,"k":[552.182,469.191]},"g":{"p":4,"k":{"a":0,"k":[0,0.447,0.353,0.749,0.364,0.353,0.271,0.659,0.721,0.294,0.212,0.6,1,0.271,0.192,0.58]}},"hd":false,"o":{"a":0,"k":100},"r":1},{"ty":"tr","p":{"a":0,"k":[526.1,469.2]},"a":{"a":0,"k":[526.1,469.2]},"s":{"a":0,"k":[100,100]},"r":{"a":0,"k":0},"o":{"a":0,"k":100},"sk":{"a":0,"k":0},"sa":{"a":0,"k":0}}],"nm":"Object","hd":false},{"ty":"gr","it":[{"ty":"sh","d":1,"ks":{"a":0,"k":{"i":[[0,0],[0,0],[0,0],[0,0],[0,0],[0,0],[0,0],[0,0]],"o":[[0,0],[0,0],[0,0],[0,0],[0,0],[0,0],[0,0],[0,0]],"v":[[447.8,466],[447.8,524.3],[446.7,524.7],[395.6,541.6],[395.6,483.4],[446.7,466.4],[446.8,466.4],[447.8,466]],"c":true},"hd":false}},{"ty":"gf","t":1,"s":{"a":0,"k":[395.622,503.841]},"e":{"a":0,"k":[447.802,503.841]},"g":{"p":4,"k":{"a":0,"k":[0,0.447,0.353,0.749,0.364,0.353,0.271,0.659,0.721,0.294,0.212,0.6,1,0.271,0.192,0.58]}},"hd":false,"o":{"a":0,"k":100},"r":1},{"ty":"tr","p":{"a":0,"k":[421.7,503.8]},"a":{"a":0,"k":[421.7,503.8]},"s":{"a":0,"k":[100,100]},"r":{"a":0,"k":0},"o":{"a":0,"k":100},"sk":{"a":0,"k":0},"sa":{"a":0,"k":0}}],"nm":"Object","hd":false},{"ty":"gr","it":[{"ty":"sh","d":1,"ks":{"a":0,"k":{"i":[[0,0],[0,0],[0,0],[0,0],[0,0],[0,0],[0,0],[0,0],[0,0],[0,0],[0,0],[0,0]],"o":[[0,0],[0,0],[0,0],[0,0],[0,0],[0,0],[0,0],[0,0],[0,0],[0,0],[0,0],[0,0]],"v":[[500,448.7],[500,507],[498.9,507.3],[498.9,507.3],[448.9,524],[448.2,524.2],[448.2,524.2],[447.8,524.3],[447.8,466],[448.9,465.7],[499.6,448.9],[500,448.7]],"c":true},"hd":false}},{"ty":"gf","t":1,"s":{"a":0,"k":[447.802,486.521]},"e":{"a":0,"k":[499.992,486.521]},"g":{"p":4,"k":{"a":0,"k":[0,0.447,0.353,0.749,0.364,0.353,0.271,0.659,0.721,0.294,0.212,0.6,1,0.271,0.192,0.58]}},"hd":false,"o":{"a":0,"k":100},"r":1},{"ty":"tr","p":{"a":0,"k":[473.9,486.5]},"a":{"a":0,"k":[473.9,486.5]},"s":{"a":0,"k":[100,100]},"r":{"a":0,"k":0},"o":{"a":0,"k":100},"sk":{"a":0,"k":0},"sa":{"a":0,"k":0}}],"nm":"Object","hd":false},{"ty":"tr","p":{"a":0,"k":[395.6,460.5]},"a":{"a":0,"k":[395.6,460.5]},"s":{"a":0,"k":[100,100]},"r":{"a":0,"k":0},"o":{"a":0,"k":100},"sk":{"a":0,"k":0},"sa":{"a":0,"k":0}}],"nm":"Object","hd":false}],"ln":"BTTM"},{"ind":1,"nm":"Layer_3","ks":{"p":{"a":1,"k":[{"t":0,"s":[226.956,7,0],"to":[0,0,0],"ti":[0,0,0],"i":{"x":[0.58],"y":[1]},"o":{"x":[0.42],"y":[0]},"e":[226.956,186.1,0]},{"t":14,"s":[226.956,186.1,0],"to":[0,0,0],"ti":[0,0,0],"i":{"x":[0.58],"y":[1]},"o":{"x":[0.42],"y":[0]},"e":[226.956,7,0]},{"t":25,"s":[226.956,7,0],"to":[0,0,0],"ti":[0,0,0],"i":{"x":[0.58],"y":[1]},"o":{"x":[0.42],"y":[0]},"e":[226.956,186.1,0]},{"t":39,"s":[226.956,186.1,0],"to":[0,0,0],"ti":[0,0,0],"i":{"x":[0.58],"y":[1]},"o":{"x":[0.42],"y":[0]},"e":[226.956,7,0]},{"t":50,"s":[226.956,7,0],"to":[0,0,0],"ti":[0,0,0],"i":{"x":[0.58],"y":[1]},"o":{"x":[0.42],"y":[0]},"e":[226.956,186.1,0]},{"t":64,"s":[226.956,186.1,0],"to":[0,0,0],"ti":[0,0,0],"i":{"x":[0.58],"y":[1]},"o":{"x":[0.42],"y":[0]},"e":[226.956,7,0]},{"t":75,"s":[226.956,7,0],"to":[0,0,0],"ti":[0,0,0],"i":{"x":[0.58],"y":[1]},"o":{"x":[0.42],"y":[0]},"e":[226.956,186.1,0]},{"t":89,"s":[226.956,186.1,0],"to":[0,0,0],"ti":[0,0,0],"i":{"x":[0.58],"y":[1]},"o":{"x":[0.42],"y":[0]},"e":[226.956,7,0]},{"t":100,"s":[226.956,7,0]}]},"a":{"a":0,"k":[390.15,214.806,0]},"s":{"a":0,"k":[100,100,100]},"r":{"a":0,"k":0},"o":{"a":0,"k":100}},"ao":0,"ip":0,"op":100,"st":0,"bm":0,"sr":1,"ty":4,"shapes":[{"ty":"gr","it":[{"ty":"gr","it":[{"ty":"sh","d":1,"ks":{"a":0,"k":{"i":[[0,0],[0,0],[0,3],[0,0],[1.8,0.5],[0,0],[0,-3],[0,0],[-1.8,-0.5]],"o":[[0,0],[2.6,0.8],[0,0],[0,-2.1],[0,0],[-2.6,-0.8],[0,0],[0,2.1],[0,0]],"v":[[347.7,240.4],[382.8,251],[387.9,246.5],[387.9,206.6],[384.9,202.1],[349.8,191.5],[344.7,196],[344.7,235.9],[347.7,240.4]],"c":true},"hd":false}},{"ty":"gf","t":1,"s":{"a":0,"k":[336.411,200.1]},"e":{"a":0,"k":[415.728,256.108]},"g":{"p":6,"k":{"a":0,"k":[0,0.894,0.616,0.784,0.155,0.741,0.525,0.773,0.344,0.584,0.431,0.761,0.493,0.482,0.373,0.753,0.584,0.447,0.353,0.749,1,0.624,0.631,0.878]}},"hd":false,"o":{"a":0,"k":100},"r":1},{"ty":"tr","p":{"a":0,"k":[366.3,221.25]},"a":{"a":0,"k":[366.3,221.25]},"s":{"a":0,"k":[100,100]},"r":{"a":0,"k":0},"o":{"a":0,"k":100},"sk":{"a":0,"k":0},"sa":{"a":0,"k":0}}],"nm":"Object","hd":false},{"ty":"gr","it":[{"ty":"sh","d":1,"ks":{"a":0,"k":{"i":[[0,0],[0,0],[0,3],[0,0],[-2,0.5],[0,0],[0,-3],[0,0],[2,-0.5]],"o":[[0,0],[-2.8,0.8],[0,0],[0,-2.1],[0,0],[2.8,-0.8],[0,0],[0,2.1],[0,0]],"v":[[432.2,240.4],[393.5,251],[387.9,246.5],[387.9,206.6],[391.3,202.1],[430,191.5],[435.6,196],[435.6,235.9],[432.2,240.4]],"c":true},"hd":false}},{"ty":"gf","t":1,"s":{"a":0,"k":[412.657,221.897]},"e":{"a":0,"k":[384.451,200.582]},"g":{"p":4,"k":{"a":0,"k":[0,0.271,0.192,0.58,0.279,0.294,0.212,0.6,0.636,0.353,0.271,0.659,1,0.447,0.353,0.749]}},"hd":false,"o":{"a":0,"k":100},"r":1},{"ty":"tr","p":{"a":0,"k":[411.75,221.25]},"a":{"a":0,"k":[411.75,221.25]},"s":{"a":0,"k":[100,100]},"r":{"a":0,"k":0},"o":{"a":0,"k":100},"sk":{"a":0,"k":0},"sa":{"a":0,"k":0}}],"nm":"Object","hd":false},{"ty":"gr","it":[{"ty":"sh","d":1,"ks":{"a":0,"k":{"i":[[0,0],[-6.5,2.7],[0,0],[0,0]],"o":[[0,0],[6.5,-2.7],[0,0],[0,0]],"v":[[382.8,251],[393.5,251],[387.9,238],[382.8,251]],"c":true},"hd":false}},{"ty":"gf","t":1,"s":{"a":0,"k":[382.78,245.054]},"e":{"a":0,"k":[395.414,245.054]},"g":{"p":4,"k":{"a":0,"k":[0,0.271,0.192,0.58,0.279,0.294,0.212,0.6,0.636,0.353,0.271,0.659,1,0.447,0.353,0.749]}},"hd":false,"o":{"a":0,"k":100},"r":1},{"ty":"tr","p":{"a":0,"k":[389.109,245.1]},"a":{"a":0,"k":[389.109,245.1]},"s":{"a":0,"k":[100,100]},"r":{"a":0,"k":0},"o":{"a":0,"k":100},"sk":{"a":0,"k":0},"sa":{"a":0,"k":0}}],"nm":"Object","hd":false},{"ty":"gr","it":[{"ty":"sh","d":1,"ks":{"a":0,"k":{"i":[[0,0],[-2.9,-0.8],[0.2,-7.2],[0,0],[-1.7,5.5],[-34.5,10.5]],"o":[[2.9,-0.9],[11.2,3.1],[-0.1,4.2],[0,0],[1.6,-4.8],[0,0]],"v":[[383.4,178.1],[392.3,178],[435.4,195],[387,208],[344.9,194],[383.4,178.1]],"c":true},"hd":false}},{"ty":"gf","t":1,"s":{"a":0,"k":[360.589,189.699]},"e":{"a":0,"k":[435.351,197.842]},"g":{"p":3,"k":{"a":0,"k":[0,0.694,0.553,0.839,0.512,0.514,0.522,0.78,1,0.447,0.353,0.749]}},"hd":false,"o":{"a":0,"k":100},"r":1},{"ty":"tr","p":{"a":0,"k":[390.126,192.706]},"a":{"a":0,"k":[390.126,192.706]},"s":{"a":0,"k":[100,100]},"r":{"a":0,"k":0},"o":{"a":0,"k":100},"sk":{"a":0,"k":0},"sa":{"a":0,"k":0}}],"nm":"Object","hd":false},{"ty":"tr","p":{"a":0,"k":[390.15,214.806]},"a":{"a":0,"k":[390.15,214.806]},"s":{"a":0,"k":[100,100]},"r":{"a":0,"k":0},"o":{"a":0,"k":100},"sk":{"a":0,"k":0},"sa":{"a":0,"k":0}}],"nm":"Object","hd":false}],"ln":"Layer_3"}],"markers":[]}